{"text": "Mechanism ID: M001\nTitle: Mo2C carbide–assisted discharge process in Li–CO2 cells\nالعنوان بالعربية: آلية التفريغ على كربيد الموليبدينوم Mo₂C في بطاريات Li–CO₂\n\nEnglish description:\nThis mechanism describes how Mo2C carbide participates in the discharge process of a Li–CO2 battery. \nCO2 from the gas phase is adsorbed on the catalytic surface, reacts with Li+ and electrons, \nand forms solid discharge products such as Li2CO3 together with other intermediates \n(LiCO2, CO2−•, Li2C2O4, Li2O, CO(ads)). The exact pathway and energy barriers depend on the catalyst surface, \ndefect density, and the local electrolyte environment.\n\nالوصف بالعربية (مختصر):\nتشرح هذه الآلية كيف يساهم كربيد الموليبدينوم Mo₂C في آلية التفريغ داخل خلية Li–CO₂. \nيُمتص غاز CO₂ على السطح النشط، ثم يتفاعل مع أيونات الليثيوم والإلكترونات لتكوين نواتج \nمثل Li₂CO₃ وبعض الأنواع الوسيطة (LiCO2, CO2−•, Li2C2O4, Li2O, CO(ads)). \nشكل السطح والعيوب وبيئة الإلكتروليت تؤثر جميعها في مسار التفاعل وطاقات الحواجز.\n\nKey steps (English, schematic):\n1. CO2(g) → CO2(ads) on Mo2C carbide surface.\n2. CO2(ads) + e− + Li+ → LiCO2-like intermediate.\n3. Coupling and further reduction form Li2CO3 and possibly CO-containing species.\n4. During charge, Li2CO3 is decomposed on catalytic sites, releasing CO2 (and sometimes O2).\n\nالخطوات الرئيسية (بالعربية بشكل مبسّط):\n1- امتصاص CO₂ من الطور الغازي على سطح كربيد الموليبدينوم Mo₂C.\n2- انتقال الإلكترونات وأيونات Li⁺ لتكوين نوع وسيط مشابه لـ LiCO₂.\n3- تَحوُّل الأنواع الوسيطة إلى Li₂CO₃ ونواتج أخرى حاوية على الكربون.\n4- في الشحن، يساعد السطح التحفيزي على تفكيك Li₂CO₃ وإعادة إطلاق CO₂.\n", "metadata": {"mechanism_id": "M001", "focus_catalyst": "Mo2C carbide", "focus_catalyst_ar": "كربيد الموليبدينوم Mo₂C", "mechanism_topic_en": "discharge process", "mechanism_topic_ar": "آلية التفريغ", "main_intermediates": ["LiCO2", "CO2−•", "Li2C2O4", "Li2O", "CO(ads)"], "barrier_range_eV": [0.265, 0.563], "overpotential_trend": "High during charge, moderate during discharge", "evidence_type": ["DFT-style analysis (synthetic)", "Conceptual mechanism"], "chunk_type": "mechanism_bilingual"}}
{"text": "Mechanism ID: M002\nTitle: COF host with N-doped linkers–assisted discharge process in Li–CO2 cells\nالعنوان بالعربية: آلية التفريغ على إطار عضوي تساهمي بروابط غنية بالنيتروجين في بطاريات Li–CO₂\n\nEnglish description:\nThis mechanism describes how COF host with N-doped linkers participates in the discharge process of a Li–CO2 battery. \nCO2 from the gas phase is adsorbed on the catalytic surface, reacts with Li+ and electrons, \nand forms solid discharge products such as Li2CO3 together with other intermediates \n(CO2(ads), CO2−•, Li2C2O4). The exact pathway and energy barriers depend on the catalyst surface, \ndefect density, and the local electrolyte environment.\n\nالوصف بالعربية (مختصر):\nتشرح هذه الآلية كيف يساهم إطار عضوي تساهمي بروابط غنية بالنيتروجين في آلية التفريغ داخل خلية Li–CO₂. \nيُمتص غاز CO₂ على السطح النشط، ثم يتفاعل مع أيونات الليثيوم والإلكترونات لتكوين نواتج \nمثل Li₂CO₃ وبعض الأنواع الوسيطة (CO2(ads), CO2−•, Li2C2O4). \nشكل السطح والعيوب وبيئة الإلكتروليت تؤثر جميعها في مسار التفاعل وطاقات الحواجز.\n\nKey steps (English, schematic):\n1. CO2(g) → CO2(ads) on COF host with N-doped linkers surface.\n2. CO2(ads) + e− + Li+ → LiCO2-like intermediate.\n3. Coupling and further reduction form Li2CO3 and possibly CO-containing species.\n4. During charge, Li2CO3 is decomposed on catalytic sites, releasing CO2 (and sometimes O2).\n\nالخطوات الرئيسية (بالعربية بشكل مبسّط):\n1- امتصاص CO₂ من الطور الغازي على سطح إطار عضوي تساهمي بروابط غنية بالنيتروجين.\n2- انتقال الإلكترونات وأيونات Li⁺ لتكوين نوع وسيط مشابه لـ LiCO₂.\n3- تَحوُّل الأنواع الوسيطة إلى Li₂CO₃ ونواتج أخرى حاوية على الكربون.\n4- في الشحن، يساعد السطح التحفيزي على تفكيك Li₂CO₃ وإعادة إطلاق CO₂.\n", "metadata": {"mechanism_id": "M002", "focus_catalyst": "COF host with N-doped linkers", "focus_catalyst_ar": "إطار عضوي تساهمي بروابط غنية بالنيتروجين", "mechanism_topic_en": "discharge process", "mechanism_topic_ar": "آلية التفريغ", "main_intermediates": ["CO2(ads)", "CO2−•", "Li2C2O4"], "barrier_range_eV": [0.326, 0.481], "overpotential_trend": "Moderately reduced vs. pure carbon", "evidence_type": ["DFT-style analysis (synthetic)", "Conceptual mechanism"], "chunk_type": "mechanism_bilingual"}}
{"text": "Mechanism ID: M003\nTitle: COF host with N-doped linkers–assisted charge process in Li–CO2 cells\nالعنوان بالعربية: آلية الشحن على إطار عضوي تساهمي بروابط غنية بالنيتروجين في بطاريات Li–CO₂\n\nEnglish description:\nThis mechanism describes how COF host with N-doped linkers participates in the charge process of a Li–CO2 battery. \nCO2 from the gas phase is adsorbed on the catalytic surface, reacts with Li+ and electrons, \nand forms solid discharge products such as Li2CO3 together with other intermediates \n(Li2O, LiCO2, CO2(ads), CO2−•). The exact pathway and energy barriers depend on the catalyst surface, \ndefect density, and the local electrolyte environment.\n\nالوصف بالعربية (مختصر):\nتشرح هذه الآلية كيف يساهم إطار عضوي تساهمي بروابط غنية بالنيتروجين في آلية الشحن داخل خلية Li–CO₂. \nيُمتص غاز CO₂ على السطح النشط، ثم يتفاعل مع أيونات الليثيوم والإلكترونات لتكوين نواتج \nمثل Li₂CO₃ وبعض الأنواع الوسيطة (Li2O, LiCO2, CO2(ads), CO2−•). \nشكل السطح والعيوب وبيئة الإلكتروليت تؤثر جميعها في مسار التفاعل وطاقات الحواجز.\n\nKey steps (English, schematic):\n1. CO2(g) → CO2(ads) on COF host with N-doped linkers surface.\n2. CO2(ads) + e− + Li+ → LiCO2-like intermediate.\n3. Coupling and further reduction form Li2CO3 and possibly CO-containing species.\n4. During charge, Li2CO3 is decomposed on catalytic sites, releasing CO2 (and sometimes O2).\n\nالخطوات الرئيسية (بالعربية بشكل مبسّط):\n1- امتصاص CO₂ من الطور الغازي على سطح إطار عضوي تساهمي بروابط غنية بالنيتروجين.\n2- انتقال الإلكترونات وأيونات Li⁺ لتكوين نوع وسيط مشابه لـ LiCO₂.\n3- تَحوُّل الأنواع الوسيطة إلى Li₂CO₃ ونواتج أخرى حاوية على الكربون.\n4- في الشحن، يساعد السطح التحفيزي على تفكيك Li₂CO₃ وإعادة إطلاق CO₂.\n", "metadata": {"mechanism_id": "M003", "focus_catalyst": "COF host with N-doped linkers", "focus_catalyst_ar": "إطار عضوي تساهمي بروابط غنية بالنيتروجين", "mechanism_topic_en": "charge process", "mechanism_topic_ar": "آلية الشحن", "main_intermediates": ["Li2O", "LiCO2", "CO2(ads)", "CO2−•"], "barrier_range_eV": [0.355, 0.573], "overpotential_trend": "Moderately reduced vs. pure carbon", "evidence_type": ["DFT-style analysis (synthetic)", "Conceptual mechanism"], "chunk_type": "mechanism_bilingual"}}
{"text": "Mechanism ID: M004\nTitle: Co/Mn spinel oxide–assisted full Li–CO2 cycle in Li–CO2 cells\nالعنوان بالعربية: الدورة الكاملة في خلية Li–CO₂ على أكاسيد سبينل الكوبالت/المنغنيز في بطاريات Li–CO₂\n\nEnglish description:\nThis mechanism describes how Co/Mn spinel oxide participates in the full Li–CO2 cycle of a Li–CO2 battery. \nCO2 from the gas phase is adsorbed on the catalytic surface, reacts with Li+ and electrons, \nand forms solid discharge products such as Li2CO3 together with other intermediates \n(CO2(ads), Li2CO3, CO(ads)). The exact pathway and energy barriers depend on the catalyst surface, \ndefect density, and the local electrolyte environment.\n\nالوصف بالعربية (مختصر):\nتشرح هذه الآلية كيف يساهم أكاسيد سبينل الكوبالت/المنغنيز في الدورة الكاملة في خلية Li–CO₂ داخل خلية Li–CO₂. \nيُمتص غاز CO₂ على السطح النشط، ثم يتفاعل مع أيونات الليثيوم والإلكترونات لتكوين نواتج \nمثل Li₂CO₃ وبعض الأنواع الوسيطة (CO2(ads), Li2CO3, CO(ads)). \nشكل السطح والعيوب وبيئة الإلكتروليت تؤثر جميعها في مسار التفاعل وطاقات الحواجز.\n\nKey steps (English, schematic):\n1. CO2(g) → CO2(ads) on Co/Mn spinel oxide surface.\n2. CO2(ads) + e− + Li+ → LiCO2-like intermediate.\n3. Coupling and further reduction form Li2CO3 and possibly CO-containing species.\n4. During charge, Li2CO3 is decomposed on catalytic sites, releasing CO2 (and sometimes O2).\n\nالخطوات الرئيسية (بالعربية بشكل مبسّط):\n1- امتصاص CO₂ من الطور الغازي على سطح أكاسيد سبينل الكوبالت/المنغنيز.\n2- انتقال الإلكترونات وأيونات Li⁺ لتكوين نوع وسيط مشابه لـ LiCO₂.\n3- تَحوُّل الأنواع الوسيطة إلى Li₂CO₃ ونواتج أخرى حاوية على الكربون.\n4- في الشحن، يساعد السطح التحفيزي على تفكيك Li₂CO₃ وإعادة إطلاق CO₂.\n", "metadata": {"mechanism_id": "M004", "focus_catalyst": "Co/Mn spinel oxide", "focus_catalyst_ar": "أكاسيد سبينل الكوبالت/المنغنيز", "mechanism_topic_en": "full Li–CO2 cycle", "mechanism_topic_ar": "الدورة الكاملة في خلية Li–CO₂", "main_intermediates": ["CO2(ads)", "Li2CO3", "CO(ads)"], "barrier_range_eV": [0.304, 0.523], "overpotential_trend": "Significantly reduced when catalyst is well dispersed", "evidence_type": ["DFT-style analysis (synthetic)", "Conceptual mechanism"], "chunk_type": "mechanism_bilingual"}}
{"text": "Mechanism ID: M005\nTitle: Porous carbon–assisted side reactions and by-products in Li–CO2 cells\nالعنوان بالعربية: التفاعلات الجانبية والنواتج الثانوية على الكربون المسامي في بطاريات Li–CO₂\n\nEnglish description:\nThis mechanism describes how Porous carbon participates in the side reactions and by-products of a Li–CO2 battery. \nCO2 from the gas phase is adsorbed on the catalytic surface, reacts with Li+ and electrons, \nand forms solid discharge products such as Li2CO3 together with other intermediates \n(CO2(ads), Li2CO3, CO(ads), LiCO2, Li2C2O4). The exact pathway and energy barriers depend on the catalyst surface, \ndefect density, and the local electrolyte environment.\n\nالوصف بالعربية (مختصر):\nتشرح هذه الآلية كيف يساهم الكربون المسامي في التفاعلات الجانبية والنواتج الثانوية داخل خلية Li–CO₂. \nيُمتص غاز CO₂ على السطح النشط، ثم يتفاعل مع أيونات الليثيوم والإلكترونات لتكوين نواتج \nمثل Li₂CO₃ وبعض الأنواع الوسيطة (CO2(ads), Li2CO3, CO(ads), LiCO2, Li2C2O4). \nشكل السطح والعيوب وبيئة الإلكتروليت تؤثر جميعها في مسار التفاعل وطاقات الحواجز.\n\nKey steps (English, schematic):\n1. CO2(g) → CO2(ads) on Porous carbon surface.\n2. CO2(ads) + e− + Li+ → LiCO2-like intermediate.\n3. Coupling and further reduction form Li2CO3 and possibly CO-containing species.\n4. During charge, Li2CO3 is decomposed on catalytic sites, releasing CO2 (and sometimes O2).\n\nالخطوات الرئيسية (بالعربية بشكل مبسّط):\n1- امتصاص CO₂ من الطور الغازي على سطح الكربون المسامي.\n2- انتقال الإلكترونات وأيونات Li⁺ لتكوين نوع وسيط مشابه لـ LiCO₂.\n3- تَحوُّل الأنواع الوسيطة إلى Li₂CO₃ ونواتج أخرى حاوية على الكربون.\n4- في الشحن، يساعد السطح التحفيزي على تفكيك Li₂CO₃ وإعادة إطلاق CO₂.\n", "metadata": {"mechanism_id": "M005", "focus_catalyst": "Porous carbon", "focus_catalyst_ar": "الكربون المسامي", "mechanism_topic_en": "side reactions and by-products", "mechanism_topic_ar": "التفاعلات الجانبية والنواتج الثانوية", "main_intermediates": ["CO2(ads)", "Li2CO3", "CO(ads)", "LiCO2", "Li2C2O4"], "barrier_range_eV": [0.343, 0.665], "overpotential_trend": "Moderately reduced vs. pure carbon", "evidence_type": ["DFT-style analysis (synthetic)", "Conceptual mechanism"], "chunk_type": "mechanism_bilingual"}}
{"text": "Mechanism ID: M006\nTitle: Mo2C carbide–assisted discharge process in Li–CO2 cells\nالعنوان بالعربية: آلية التفريغ على كربيد الموليبدينوم Mo₂C في بطاريات Li–CO₂\n\nEnglish description:\nThis mechanism describes how Mo2C carbide participates in the discharge process of a Li–CO2 battery. \nCO2 from the gas phase is adsorbed on the catalytic surface, reacts with Li+ and electrons, \nand forms solid discharge products such as Li2CO3 together with other intermediates \n(CO2−•, LiCO2, CO2(ads), CO(ads), Li2O). The exact pathway and energy barriers depend on the catalyst surface, \ndefect density, and the local electrolyte environment.\n\nالوصف بالعربية (مختصر):\nتشرح هذه الآلية كيف يساهم كربيد الموليبدينوم Mo₂C في آلية التفريغ داخل خلية Li–CO₂. \nيُمتص غاز CO₂ على السطح النشط، ثم يتفاعل مع أيونات الليثيوم والإلكترونات لتكوين نواتج \nمثل Li₂CO₃ وبعض الأنواع الوسيطة (CO2−•, LiCO2, CO2(ads), CO(ads), Li2O). \nشكل السطح والعيوب وبيئة الإلكتروليت تؤثر جميعها في مسار التفاعل وطاقات الحواجز.\n\nKey steps (English, schematic):\n1. CO2(g) → CO2(ads) on Mo2C carbide surface.\n2. CO2(ads) + e− + Li+ → LiCO2-like intermediate.\n3. Coupling and further reduction form Li2CO3 and possibly CO-containing species.\n4. During charge, Li2CO3 is decomposed on catalytic sites, releasing CO2 (and sometimes O2).\n\nالخطوات الرئيسية (بالعربية بشكل مبسّط):\n1- امتصاص CO₂ من الطور الغازي على سطح كربيد الموليبدينوم Mo₂C.\n2- انتقال الإلكترونات وأيونات Li⁺ لتكوين نوع وسيط مشابه لـ LiCO₂.\n3- تَحوُّل الأنواع الوسيطة إلى Li₂CO₃ ونواتج أخرى حاوية على الكربون.\n4- في الشحن، يساعد السطح التحفيزي على تفكيك Li₂CO₃ وإعادة إطلاق CO₂.\n", "metadata": {"mechanism_id": "M006", "focus_catalyst": "Mo2C carbide", "focus_catalyst_ar": "كربيد الموليبدينوم Mo₂C", "mechanism_topic_en": "discharge process", "mechanism_topic_ar": "آلية التفريغ", "main_intermediates": ["CO2−•", "LiCO2", "CO2(ads)", "CO(ads)", "Li2O"], "barrier_range_eV": [0.307, 0.548], "overpotential_trend": "Significantly reduced when catalyst is well dispersed", "evidence_type": ["DFT-style analysis (synthetic)", "Conceptual mechanism"], "chunk_type": "mechanism_bilingual"}}
{"text": "Mechanism ID: M007\nTitle: Ru single-atom sites–assisted full Li–CO2 cycle in Li–CO2 cells\nالعنوان بالعربية: الدورة الكاملة في خلية Li–CO₂ على مواقع الروثينيوم أحادي الذرة في بطاريات Li–CO₂\n\nEnglish description:\nThis mechanism describes how Ru single-atom sites participates in the full Li–CO2 cycle of a Li–CO2 battery. \nCO2 from the gas phase is adsorbed on the catalytic surface, reacts with Li+ and electrons, \nand forms solid discharge products such as Li2CO3 together with other intermediates \n(CO2−•, Li2C2O4, LiCO2, CO2(ads)). The exact pathway and energy barriers depend on the catalyst surface, \ndefect density, and the local electrolyte environment.\n\nالوصف بالعربية (مختصر):\nتشرح هذه الآلية كيف يساهم مواقع الروثينيوم أحادي الذرة في الدورة الكاملة في خلية Li–CO₂ داخل خلية Li–CO₂. \nيُمتص غاز CO₂ على السطح النشط، ثم يتفاعل مع أيونات الليثيوم والإلكترونات لتكوين نواتج \nمثل Li₂CO₃ وبعض الأنواع الوسيطة (CO2−•, Li2C2O4, LiCO2, CO2(ads)). \nشكل السطح والعيوب وبيئة الإلكتروليت تؤثر جميعها في مسار التفاعل وطاقات الحواجز.\n\nKey steps (English, schematic):\n1. CO2(g) → CO2(ads) on Ru single-atom sites surface.\n2. CO2(ads) + e− + Li+ → LiCO2-like intermediate.\n3. Coupling and further reduction form Li2CO3 and possibly CO-containing species.\n4. During charge, Li2CO3 is decomposed on catalytic sites, releasing CO2 (and sometimes O2).\n\nالخطوات الرئيسية (بالعربية بشكل مبسّط):\n1- امتصاص CO₂ من الطور الغازي على سطح مواقع الروثينيوم أحادي الذرة.\n2- انتقال الإلكترونات وأيونات Li⁺ لتكوين نوع وسيط مشابه لـ LiCO₂.\n3- تَحوُّل الأنواع الوسيطة إلى Li₂CO₃ ونواتج أخرى حاوية على الكربون.\n4- في الشحن، يساعد السطح التحفيزي على تفكيك Li₂CO₃ وإعادة إطلاق CO₂.\n", "metadata": {"mechanism_id": "M007", "focus_catalyst": "Ru single-atom sites", "focus_catalyst_ar": "مواقع الروثينيوم أحادي الذرة", "mechanism_topic_en": "full Li–CO2 cycle", "mechanism_topic_ar": "الدورة الكاملة في خلية Li–CO₂", "main_intermediates": ["CO2−•", "Li2C2O4", "LiCO2", "CO2(ads)"], "barrier_range_eV": [0.341, 0.525], "overpotential_trend": "Moderately reduced vs. pure carbon", "evidence_type": ["DFT-style analysis (synthetic)", "Conceptual mechanism"], "chunk_type": "mechanism_bilingual"}}
{"text": "Mechanism ID: M008\nTitle: Ru single-atom sites–assisted side reactions and by-products in Li–CO2 cells\nالعنوان بالعربية: التفاعلات الجانبية والنواتج الثانوية على مواقع الروثينيوم أحادي الذرة في بطاريات Li–CO₂\n\nEnglish description:\nThis mechanism describes how Ru single-atom sites participates in the side reactions and by-products of a Li–CO2 battery. \nCO2 from the gas phase is adsorbed on the catalytic surface, reacts with Li+ and electrons, \nand forms solid discharge products such as Li2CO3 together with other intermediates \n(LiCO2, Li2C2O4, Li2O, CO2−•). The exact pathway and energy barriers depend on the catalyst surface, \ndefect density, and the local electrolyte environment.\n\nالوصف بالعربية (مختصر):\nتشرح هذه الآلية كيف يساهم مواقع الروثينيوم أحادي الذرة في التفاعلات الجانبية والنواتج الثانوية داخل خلية Li–CO₂. \nيُمتص غاز CO₂ على السطح النشط، ثم يتفاعل مع أيونات الليثيوم والإلكترونات لتكوين نواتج \nمثل Li₂CO₃ وبعض الأنواع الوسيطة (LiCO2, Li2C2O4, Li2O, CO2−•). \nشكل السطح والعيوب وبيئة الإلكتروليت تؤثر جميعها في مسار التفاعل وطاقات الحواجز.\n\nKey steps (English, schematic):\n1. CO2(g) → CO2(ads) on Ru single-atom sites surface.\n2. CO2(ads) + e− + Li+ → LiCO2-like intermediate.\n3. Coupling and further reduction form Li2CO3 and possibly CO-containing species.\n4. During charge, Li2CO3 is decomposed on catalytic sites, releasing CO2 (and sometimes O2).\n\nالخطوات الرئيسية (بالعربية بشكل مبسّط):\n1- امتصاص CO₂ من الطور الغازي على سطح مواقع الروثينيوم أحادي الذرة.\n2- انتقال الإلكترونات وأيونات Li⁺ لتكوين نوع وسيط مشابه لـ LiCO₂.\n3- تَحوُّل الأنواع الوسيطة إلى Li₂CO₃ ونواتج أخرى حاوية على الكربون.\n4- في الشحن، يساعد السطح التحفيزي على تفكيك Li₂CO₃ وإعادة إطلاق CO₂.\n", "metadata": {"mechanism_id": "M008", "focus_catalyst": "Ru single-atom sites", "focus_catalyst_ar": "مواقع الروثينيوم أحادي الذرة", "mechanism_topic_en": "side reactions and by-products", "mechanism_topic_ar": "التفاعلات الجانبية والنواتج الثانوية", "main_intermediates": ["LiCO2", "Li2C2O4", "Li2O", "CO2−•"], "barrier_range_eV": [0.353, 0.672], "overpotential_trend": "High during charge, moderate during discharge", "evidence_type": ["DFT-style analysis (synthetic)", "Conceptual mechanism"], "chunk_type": "mechanism_bilingual"}}
{"text": "Mechanism ID: M009\nTitle: Co/Mn spinel oxide–assisted discharge process in Li–CO2 cells\nالعنوان بالعربية: آلية التفريغ على أكاسيد سبينل الكوبالت/المنغنيز في بطاريات Li–CO₂\n\nEnglish description:\nThis mechanism describes how Co/Mn spinel oxide participates in the discharge process of a Li–CO2 battery. \nCO2 from the gas phase is adsorbed on the catalytic surface, reacts with Li+ and electrons, \nand forms solid discharge products such as Li2CO3 together with other intermediates \n(Li2CO3, LiCO2, CO2(ads), CO2−•). The exact pathway and energy barriers depend on the catalyst surface, \ndefect density, and the local electrolyte environment.\n\nالوصف بالعربية (مختصر):\nتشرح هذه الآلية كيف يساهم أكاسيد سبينل الكوبالت/المنغنيز في آلية التفريغ داخل خلية Li–CO₂. \nيُمتص غاز CO₂ على السطح النشط، ثم يتفاعل مع أيونات الليثيوم والإلكترونات لتكوين نواتج \nمثل Li₂CO₃ وبعض الأنواع الوسيطة (Li2CO3, LiCO2, CO2(ads), CO2−•). \nشكل السطح والعيوب وبيئة الإلكتروليت تؤثر جميعها في مسار التفاعل وطاقات الحواجز.\n\nKey steps (English, schematic):\n1. CO2(g) → CO2(ads) on Co/Mn spinel oxide surface.\n2. CO2(ads) + e− + Li+ → LiCO2-like intermediate.\n3. Coupling and further reduction form Li2CO3 and possibly CO-containing species.\n4. During charge, Li2CO3 is decomposed on catalytic sites, releasing CO2 (and sometimes O2).\n\nالخطوات الرئيسية (بالعربية بشكل مبسّط):\n1- امتصاص CO₂ من الطور الغازي على سطح أكاسيد سبينل الكوبالت/المنغنيز.\n2- انتقال الإلكترونات وأيونات Li⁺ لتكوين نوع وسيط مشابه لـ LiCO₂.\n3- تَحوُّل الأنواع الوسيطة إلى Li₂CO₃ ونواتج أخرى حاوية على الكربون.\n4- في الشحن، يساعد السطح التحفيزي على تفكيك Li₂CO₃ وإعادة إطلاق CO₂.\n", "metadata": {"mechanism_id": "M009", "focus_catalyst": "Co/Mn spinel oxide", "focus_catalyst_ar": "أكاسيد سبينل الكوبالت/المنغنيز", "mechanism_topic_en": "discharge process", "mechanism_topic_ar": "آلية التفريغ", "main_intermediates": ["Li2CO3", "LiCO2", "CO2(ads)", "CO2−•"], "barrier_range_eV": [0.387, 0.65], "overpotential_trend": "Significantly reduced when catalyst is well dispersed", "evidence_type": ["DFT-style analysis (synthetic)", "Conceptual mechanism"], "chunk_type": "mechanism_bilingual"}}
{"text": "Mechanism ID: M010\nTitle: Co/Mn spinel oxide–assisted side reactions and by-products in Li–CO2 cells\nالعنوان بالعربية: التفاعلات الجانبية والنواتج الثانوية على أكاسيد سبينل الكوبالت/المنغنيز في بطاريات Li–CO₂\n\nEnglish description:\nThis mechanism describes how Co/Mn spinel oxide participates in the side reactions and by-products of a Li–CO2 battery. \nCO2 from the gas phase is adsorbed on the catalytic surface, reacts with Li+ and electrons, \nand forms solid discharge products such as Li2CO3 together with other intermediates \n(Li2C2O4, Li2CO3, CO2−•, LiCO2). The exact pathway and energy barriers depend on the catalyst surface, \ndefect density, and the local electrolyte environment.\n\nالوصف بالعربية (مختصر):\nتشرح هذه الآلية كيف يساهم أكاسيد سبينل الكوبالت/المنغنيز في التفاعلات الجانبية والنواتج الثانوية داخل خلية Li–CO₂. \nيُمتص غاز CO₂ على السطح النشط، ثم يتفاعل مع أيونات الليثيوم والإلكترونات لتكوين نواتج \nمثل Li₂CO₃ وبعض الأنواع الوسيطة (Li2C2O4, Li2CO3, CO2−•, LiCO2). \nشكل السطح والعيوب وبيئة الإلكتروليت تؤثر جميعها في مسار التفاعل وطاقات الحواجز.\n\nKey steps (English, schematic):\n1. CO2(g) → CO2(ads) on Co/Mn spinel oxide surface.\n2. CO2(ads) + e− + Li+ → LiCO2-like intermediate.\n3. Coupling and further reduction form Li2CO3 and possibly CO-containing species.\n4. During charge, Li2CO3 is decomposed on catalytic sites, releasing CO2 (and sometimes O2).\n\nالخطوات الرئيسية (بالعربية بشكل مبسّط):\n1- امتصاص CO₂ من الطور الغازي على سطح أكاسيد سبينل الكوبالت/المنغنيز.\n2- انتقال الإلكترونات وأيونات Li⁺ لتكوين نوع وسيط مشابه لـ LiCO₂.\n3- تَحوُّل الأنواع الوسيطة إلى Li₂CO₃ ونواتج أخرى حاوية على الكربون.\n4- في الشحن، يساعد السطح التحفيزي على تفكيك Li₂CO₃ وإعادة إطلاق CO₂.\n", "metadata": {"mechanism_id": "M010", "focus_catalyst": "Co/Mn spinel oxide", "focus_catalyst_ar": "أكاسيد سبينل الكوبالت/المنغنيز", "mechanism_topic_en": "side reactions and by-products", "mechanism_topic_ar": "التفاعلات الجانبية والنواتج الثانوية", "main_intermediates": ["Li2C2O4", "Li2CO3", "CO2−•", "LiCO2"], "barrier_range_eV": [0.271, 0.57], "overpotential_trend": "Significantly reduced when catalyst is well dispersed", "evidence_type": ["DFT-style analysis (synthetic)", "Conceptual mechanism"], "chunk_type": "mechanism_bilingual"}}
{"text": "Mechanism ID: M011\nTitle: COF host with N-doped linkers–assisted side reactions and by-products in Li–CO2 cells\nالعنوان بالعربية: التفاعلات الجانبية والنواتج الثانوية على إطار عضوي تساهمي بروابط غنية بالنيتروجين في بطاريات Li–CO₂\n\nEnglish description:\nThis mechanism describes how COF host with N-doped linkers participates in the side reactions and by-products of a Li–CO2 battery. \nCO2 from the gas phase is adsorbed on the catalytic surface, reacts with Li+ and electrons, \nand forms solid discharge products such as Li2CO3 together with other intermediates \n(CO2−•, CO(ads), Li2O, Li2CO3). The exact pathway and energy barriers depend on the catalyst surface, \ndefect density, and the local electrolyte environment.\n\nالوصف بالعربية (مختصر):\nتشرح هذه الآلية كيف يساهم إطار عضوي تساهمي بروابط غنية بالنيتروجين في التفاعلات الجانبية والنواتج الثانوية داخل خلية Li–CO₂. \nيُمتص غاز CO₂ على السطح النشط، ثم يتفاعل مع أيونات الليثيوم والإلكترونات لتكوين نواتج \nمثل Li₂CO₃ وبعض الأنواع الوسيطة (CO2−•, CO(ads), Li2O, Li2CO3). \nشكل السطح والعيوب وبيئة الإلكتروليت تؤثر جميعها في مسار التفاعل وطاقات الحواجز.\n\nKey steps (English, schematic):\n1. CO2(g) → CO2(ads) on COF host with N-doped linkers surface.\n2. CO2(ads) + e− + Li+ → LiCO2-like intermediate.\n3. Coupling and further reduction form Li2CO3 and possibly CO-containing species.\n4. During charge, Li2CO3 is decomposed on catalytic sites, releasing CO2 (and sometimes O2).\n\nالخطوات الرئيسية (بالعربية بشكل مبسّط):\n1- امتصاص CO₂ من الطور الغازي على سطح إطار عضوي تساهمي بروابط غنية بالنيتروجين.\n2- انتقال الإلكترونات وأيونات Li⁺ لتكوين نوع وسيط مشابه لـ LiCO₂.\n3- تَحوُّل الأنواع الوسيطة إلى Li₂CO₃ ونواتج أخرى حاوية على الكربون.\n4- في الشحن، يساعد السطح التحفيزي على تفكيك Li₂CO₃ وإعادة إطلاق CO₂.\n", "metadata": {"mechanism_id": "M011", "focus_catalyst": "COF host with N-doped linkers", "focus_catalyst_ar": "إطار عضوي تساهمي بروابط غنية بالنيتروجين", "mechanism_topic_en": "side reactions and by-products", "mechanism_topic_ar": "التفاعلات الجانبية والنواتج الثانوية", "main_intermediates": ["CO2−•", "CO(ads)", "Li2O", "Li2CO3"], "barrier_range_eV": [0.264, 0.423], "overpotential_trend": "High during charge, moderate during discharge", "evidence_type": ["DFT-style analysis (synthetic)", "Conceptual mechanism"], "chunk_type": "mechanism_bilingual"}}
{"text": "Mechanism ID: M012\nTitle: Ru single-atom sites–assisted charge process in Li–CO2 cells\nالعنوان بالعربية: آلية الشحن على مواقع الروثينيوم أحادي الذرة في بطاريات Li–CO₂\n\nEnglish description:\nThis mechanism describes how Ru single-atom sites participates in the charge process of a Li–CO2 battery. \nCO2 from the gas phase is adsorbed on the catalytic surface, reacts with Li+ and electrons, \nand forms solid discharge products such as Li2CO3 together with other intermediates \n(Li2CO3, Li2O, CO2(ads), CO(ads), CO2−•). The exact pathway and energy barriers depend on the catalyst surface, \ndefect density, and the local electrolyte environment.\n\nالوصف بالعربية (مختصر):\nتشرح هذه الآلية كيف يساهم مواقع الروثينيوم أحادي الذرة في آلية الشحن داخل خلية Li–CO₂. \nيُمتص غاز CO₂ على السطح النشط، ثم يتفاعل مع أيونات الليثيوم والإلكترونات لتكوين نواتج \nمثل Li₂CO₃ وبعض الأنواع الوسيطة (Li2CO3, Li2O, CO2(ads), CO(ads), CO2−•). \nشكل السطح والعيوب وبيئة الإلكتروليت تؤثر جميعها في مسار التفاعل وطاقات الحواجز.\n\nKey steps (English, schematic):\n1. CO2(g) → CO2(ads) on Ru single-atom sites surface.\n2. CO2(ads) + e− + Li+ → LiCO2-like intermediate.\n3. Coupling and further reduction form Li2CO3 and possibly CO-containing species.\n4. During charge, Li2CO3 is decomposed on catalytic sites, releasing CO2 (and sometimes O2).\n\nالخطوات الرئيسية (بالعربية بشكل مبسّط):\n1- امتصاص CO₂ من الطور الغازي على سطح مواقع الروثينيوم أحادي الذرة.\n2- انتقال الإلكترونات وأيونات Li⁺ لتكوين نوع وسيط مشابه لـ LiCO₂.\n3- تَحوُّل الأنواع الوسيطة إلى Li₂CO₃ ونواتج أخرى حاوية على الكربون.\n4- في الشحن، يساعد السطح التحفيزي على تفكيك Li₂CO₃ وإعادة إطلاق CO₂.\n", "metadata": {"mechanism_id": "M012", "focus_catalyst": "Ru single-atom sites", "focus_catalyst_ar": "مواقع الروثينيوم أحادي الذرة", "mechanism_topic_en": "charge process", "mechanism_topic_ar": "آلية الشحن", "main_intermediates": ["Li2CO3", "Li2O", "CO2(ads)", "CO(ads)", "CO2−•"], "barrier_range_eV": [0.339, 0.583], "overpotential_trend": "Significantly reduced when catalyst is well dispersed", "evidence_type": ["DFT-style analysis (synthetic)", "Conceptual mechanism"], "chunk_type": "mechanism_bilingual"}}
{"text": "Mechanism ID: M013\nTitle: Porous carbon–assisted discharge process in Li–CO2 cells\nالعنوان بالعربية: آلية التفريغ على الكربون المسامي في بطاريات Li–CO₂\n\nEnglish description:\nThis mechanism describes how Porous carbon participates in the discharge process of a Li–CO2 battery. \nCO2 from the gas phase is adsorbed on the catalytic surface, reacts with Li+ and electrons, \nand forms solid discharge products such as Li2CO3 together with other intermediates \n(Li2O, LiCO2, Li2C2O4, CO2(ads), CO2−•). The exact pathway and energy barriers depend on the catalyst surface, \ndefect density, and the local electrolyte environment.\n\nالوصف بالعربية (مختصر):\nتشرح هذه الآلية كيف يساهم الكربون المسامي في آلية التفريغ داخل خلية Li–CO₂. \nيُمتص غاز CO₂ على السطح النشط، ثم يتفاعل مع أيونات الليثيوم والإلكترونات لتكوين نواتج \nمثل Li₂CO₃ وبعض الأنواع الوسيطة (Li2O, LiCO2, Li2C2O4, CO2(ads), CO2−•). \nشكل السطح والعيوب وبيئة الإلكتروليت تؤثر جميعها في مسار التفاعل وطاقات الحواجز.\n\nKey steps (English, schematic):\n1. CO2(g) → CO2(ads) on Porous carbon surface.\n2. CO2(ads) + e− + Li+ → LiCO2-like intermediate.\n3. Coupling and further reduction form Li2CO3 and possibly CO-containing species.\n4. During charge, Li2CO3 is decomposed on catalytic sites, releasing CO2 (and sometimes O2).\n\nالخطوات الرئيسية (بالعربية بشكل مبسّط):\n1- امتصاص CO₂ من الطور الغازي على سطح الكربون المسامي.\n2- انتقال الإلكترونات وأيونات Li⁺ لتكوين نوع وسيط مشابه لـ LiCO₂.\n3- تَحوُّل الأنواع الوسيطة إلى Li₂CO₃ ونواتج أخرى حاوية على الكربون.\n4- في الشحن، يساعد السطح التحفيزي على تفكيك Li₂CO₃ وإعادة إطلاق CO₂.\n", "metadata": {"mechanism_id": "M013", "focus_catalyst": "Porous carbon", "focus_catalyst_ar": "الكربون المسامي", "mechanism_topic_en": "discharge process", "mechanism_topic_ar": "آلية التفريغ", "main_intermediates": ["Li2O", "LiCO2", "Li2C2O4", "CO2(ads)", "CO2−•"], "barrier_range_eV": [0.315, 0.556], "overpotential_trend": "Significantly reduced when catalyst is well dispersed", "evidence_type": ["DFT-style analysis (synthetic)", "Conceptual mechanism"], "chunk_type": "mechanism_bilingual"}}
{"text": "Mechanism ID: M014\nTitle: Ru single-atom sites–assisted discharge process in Li–CO2 cells\nالعنوان بالعربية: آلية التفريغ على مواقع الروثينيوم أحادي الذرة في بطاريات Li–CO₂\n\nEnglish description:\nThis mechanism describes how Ru single-atom sites participates in the discharge process of a Li–CO2 battery. \nCO2 from the gas phase is adsorbed on the catalytic surface, reacts with Li+ and electrons, \nand forms solid discharge products such as Li2CO3 together with other intermediates \n(LiCO2, Li2C2O4, Li2O, CO2−•, CO2(ads)). The exact pathway and energy barriers depend on the catalyst surface, \ndefect density, and the local electrolyte environment.\n\nالوصف بالعربية (مختصر):\nتشرح هذه الآلية كيف يساهم مواقع الروثينيوم أحادي الذرة في آلية التفريغ داخل خلية Li–CO₂. \nيُمتص غاز CO₂ على السطح النشط، ثم يتفاعل مع أيونات الليثيوم والإلكترونات لتكوين نواتج \nمثل Li₂CO₃ وبعض الأنواع الوسيطة (LiCO2, Li2C2O4, Li2O, CO2−•, CO2(ads)). \nشكل السطح والعيوب وبيئة الإلكتروليت تؤثر جميعها في مسار التفاعل وطاقات الحواجز.\n\nKey steps (English, schematic):\n1. CO2(g) → CO2(ads) on Ru single-atom sites surface.\n2. CO2(ads) + e− + Li+ → LiCO2-like intermediate.\n3. Coupling and further reduction form Li2CO3 and possibly CO-containing species.\n4. During charge, Li2CO3 is decomposed on catalytic sites, releasing CO2 (and sometimes O2).\n\nالخطوات الرئيسية (بالعربية بشكل مبسّط):\n1- امتصاص CO₂ من الطور الغازي على سطح مواقع الروثينيوم أحادي الذرة.\n2- انتقال الإلكترونات وأيونات Li⁺ لتكوين نوع وسيط مشابه لـ LiCO₂.\n3- تَحوُّل الأنواع الوسيطة إلى Li₂CO₃ ونواتج أخرى حاوية على الكربون.\n4- في الشحن، يساعد السطح التحفيزي على تفكيك Li₂CO₃ وإعادة إطلاق CO₂.\n", "metadata": {"mechanism_id": "M014", "focus_catalyst": "Ru single-atom sites", "focus_catalyst_ar": "مواقع الروثينيوم أحادي الذرة", "mechanism_topic_en": "discharge process", "mechanism_topic_ar": "آلية التفريغ", "main_intermediates": ["LiCO2", "Li2C2O4", "Li2O", "CO2−•", "CO2(ads)"], "barrier_range_eV": [0.306, 0.488], "overpotential_trend": "High during charge, moderate during discharge", "evidence_type": ["DFT-style analysis (synthetic)", "Conceptual mechanism"], "chunk_type": "mechanism_bilingual"}}
{"text": "Mechanism ID: M015\nTitle: Cu-based MOF–assisted side reactions and by-products in Li–CO2 cells\nالعنوان بالعربية: التفاعلات الجانبية والنواتج الثانوية على إطار فلزي عضوي قائم على النحاس في بطاريات Li–CO₂\n\nEnglish description:\nThis mechanism describes how Cu-based MOF participates in the side reactions and by-products of a Li–CO2 battery. \nCO2 from the gas phase is adsorbed on the catalytic surface, reacts with Li+ and electrons, \nand forms solid discharge products such as Li2CO3 together with other intermediates \n(CO2(ads), LiCO2, Li2C2O4). The exact pathway and energy barriers depend on the catalyst surface, \ndefect density, and the local electrolyte environment.\n\nالوصف بالعربية (مختصر):\nتشرح هذه الآلية كيف يساهم إطار فلزي عضوي قائم على النحاس في التفاعلات الجانبية والنواتج الثانوية داخل خلية Li–CO₂. \nيُمتص غاز CO₂ على السطح النشط، ثم يتفاعل مع أيونات الليثيوم والإلكترونات لتكوين نواتج \nمثل Li₂CO₃ وبعض الأنواع الوسيطة (CO2(ads), LiCO2, Li2C2O4). \nشكل السطح والعيوب وبيئة الإلكتروليت تؤثر جميعها في مسار التفاعل وطاقات الحواجز.\n\nKey steps (English, schematic):\n1. CO2(g) → CO2(ads) on Cu-based MOF surface.\n2. CO2(ads) + e− + Li+ → LiCO2-like intermediate.\n3. Coupling and further reduction form Li2CO3 and possibly CO-containing species.\n4. During charge, Li2CO3 is decomposed on catalytic sites, releasing CO2 (and sometimes O2).\n\nالخطوات الرئيسية (بالعربية بشكل مبسّط):\n1- امتصاص CO₂ من الطور الغازي على سطح إطار فلزي عضوي قائم على النحاس.\n2- انتقال الإلكترونات وأيونات Li⁺ لتكوين نوع وسيط مشابه لـ LiCO₂.\n3- تَحوُّل الأنواع الوسيطة إلى Li₂CO₃ ونواتج أخرى حاوية على الكربون.\n4- في الشحن، يساعد السطح التحفيزي على تفكيك Li₂CO₃ وإعادة إطلاق CO₂.\n", "metadata": {"mechanism_id": "M015", "focus_catalyst": "Cu-based MOF", "focus_catalyst_ar": "إطار فلزي عضوي قائم على النحاس", "mechanism_topic_en": "side reactions and by-products", "mechanism_topic_ar": "التفاعلات الجانبية والنواتج الثانوية", "main_intermediates": ["CO2(ads)", "LiCO2", "Li2C2O4"], "barrier_range_eV": [0.286, 0.484], "overpotential_trend": "High during charge, moderate during discharge", "evidence_type": ["DFT-style analysis (synthetic)", "Conceptual mechanism"], "chunk_type": "mechanism_bilingual"}}
{"text": "Mechanism ID: M016\nTitle: Mo2C carbide–assisted side reactions and by-products in Li–CO2 cells\nالعنوان بالعربية: التفاعلات الجانبية والنواتج الثانوية على كربيد الموليبدينوم Mo₂C في بطاريات Li–CO₂\n\nEnglish description:\nThis mechanism describes how Mo2C carbide participates in the side reactions and by-products of a Li–CO2 battery. \nCO2 from the gas phase is adsorbed on the catalytic surface, reacts with Li+ and electrons, \nand forms solid discharge products such as Li2CO3 together with other intermediates \n(CO(ads), Li2O, CO2−•). The exact pathway and energy barriers depend on the catalyst surface, \ndefect density, and the local electrolyte environment.\n\nالوصف بالعربية (مختصر):\nتشرح هذه الآلية كيف يساهم كربيد الموليبدينوم Mo₂C في التفاعلات الجانبية والنواتج الثانوية داخل خلية Li–CO₂. \nيُمتص غاز CO₂ على السطح النشط، ثم يتفاعل مع أيونات الليثيوم والإلكترونات لتكوين نواتج \nمثل Li₂CO₃ وبعض الأنواع الوسيطة (CO(ads), Li2O, CO2−•). \nشكل السطح والعيوب وبيئة الإلكتروليت تؤثر جميعها في مسار التفاعل وطاقات الحواجز.\n\nKey steps (English, schematic):\n1. CO2(g) → CO2(ads) on Mo2C carbide surface.\n2. CO2(ads) + e− + Li+ → LiCO2-like intermediate.\n3. Coupling and further reduction form Li2CO3 and possibly CO-containing species.\n4. During charge, Li2CO3 is decomposed on catalytic sites, releasing CO2 (and sometimes O2).\n\nالخطوات الرئيسية (بالعربية بشكل مبسّط):\n1- امتصاص CO₂ من الطور الغازي على سطح كربيد الموليبدينوم Mo₂C.\n2- انتقال الإلكترونات وأيونات Li⁺ لتكوين نوع وسيط مشابه لـ LiCO₂.\n3- تَحوُّل الأنواع الوسيطة إلى Li₂CO₃ ونواتج أخرى حاوية على الكربون.\n4- في الشحن، يساعد السطح التحفيزي على تفكيك Li₂CO₃ وإعادة إطلاق CO₂.\n", "metadata": {"mechanism_id": "M016", "focus_catalyst": "Mo2C carbide", "focus_catalyst_ar": "كربيد الموليبدينوم Mo₂C", "mechanism_topic_en": "side reactions and by-products", "mechanism_topic_ar": "التفاعلات الجانبية والنواتج الثانوية", "main_intermediates": ["CO(ads)", "Li2O", "CO2−•"], "barrier_range_eV": [0.269, 0.514], "overpotential_trend": "Moderately reduced vs. pure carbon", "evidence_type": ["DFT-style analysis (synthetic)", "Conceptual mechanism"], "chunk_type": "mechanism_bilingual"}}
{"text": "Mechanism ID: M017\nTitle: Ni-rich layered oxide–assisted side reactions and by-products in Li–CO2 cells\nالعنوان بالعربية: التفاعلات الجانبية والنواتج الثانوية على أكاسيد نيكل طبقية عالية النيكل في بطاريات Li–CO₂\n\nEnglish description:\nThis mechanism describes how Ni-rich layered oxide participates in the side reactions and by-products of a Li–CO2 battery. \nCO2 from the gas phase is adsorbed on the catalytic surface, reacts with Li+ and electrons, \nand forms solid discharge products such as Li2CO3 together with other intermediates \n(Li2O, Li2C2O4, CO2−•). The exact pathway and energy barriers depend on the catalyst surface, \ndefect density, and the local electrolyte environment.\n\nالوصف بالعربية (مختصر):\nتشرح هذه الآلية كيف يساهم أكاسيد نيكل طبقية عالية النيكل في التفاعلات الجانبية والنواتج الثانوية داخل خلية Li–CO₂. \nيُمتص غاز CO₂ على السطح النشط، ثم يتفاعل مع أيونات الليثيوم والإلكترونات لتكوين نواتج \nمثل Li₂CO₃ وبعض الأنواع الوسيطة (Li2O, Li2C2O4, CO2−•). \nشكل السطح والعيوب وبيئة الإلكتروليت تؤثر جميعها في مسار التفاعل وطاقات الحواجز.\n\nKey steps (English, schematic):\n1. CO2(g) → CO2(ads) on Ni-rich layered oxide surface.\n2. CO2(ads) + e− + Li+ → LiCO2-like intermediate.\n3. Coupling and further reduction form Li2CO3 and possibly CO-containing species.\n4. During charge, Li2CO3 is decomposed on catalytic sites, releasing CO2 (and sometimes O2).\n\nالخطوات الرئيسية (بالعربية بشكل مبسّط):\n1- امتصاص CO₂ من الطور الغازي على سطح أكاسيد نيكل طبقية عالية النيكل.\n2- انتقال الإلكترونات وأيونات Li⁺ لتكوين نوع وسيط مشابه لـ LiCO₂.\n3- تَحوُّل الأنواع الوسيطة إلى Li₂CO₃ ونواتج أخرى حاوية على الكربون.\n4- في الشحن، يساعد السطح التحفيزي على تفكيك Li₂CO₃ وإعادة إطلاق CO₂.\n", "metadata": {"mechanism_id": "M017", "focus_catalyst": "Ni-rich layered oxide", "focus_catalyst_ar": "أكاسيد نيكل طبقية عالية النيكل", "mechanism_topic_en": "side reactions and by-products", "mechanism_topic_ar": "التفاعلات الجانبية والنواتج الثانوية", "main_intermediates": ["Li2O", "Li2C2O4", "CO2−•"], "barrier_range_eV": [0.357, 0.587], "overpotential_trend": "Significantly reduced when catalyst is well dispersed", "evidence_type": ["DFT-style analysis (synthetic)", "Conceptual mechanism"], "chunk_type": "mechanism_bilingual"}}
{"text": "Mechanism ID: M018\nTitle: Hybrid MOF–carbon composite–assisted side reactions and by-products in Li–CO2 cells\nالعنوان بالعربية: التفاعلات الجانبية والنواتج الثانوية على مركب هجين من MOF مع الكربون في بطاريات Li–CO₂\n\nEnglish description:\nThis mechanism describes how Hybrid MOF–carbon composite participates in the side reactions and by-products of a Li–CO2 battery. \nCO2 from the gas phase is adsorbed on the catalytic surface, reacts with Li+ and electrons, \nand forms solid discharge products such as Li2CO3 together with other intermediates \n(CO2−•, CO(ads), CO2(ads)). The exact pathway and energy barriers depend on the catalyst surface, \ndefect density, and the local electrolyte environment.\n\nالوصف بالعربية (مختصر):\nتشرح هذه الآلية كيف يساهم مركب هجين من MOF مع الكربون في التفاعلات الجانبية والنواتج الثانوية داخل خلية Li–CO₂. \nيُمتص غاز CO₂ على السطح النشط، ثم يتفاعل مع أيونات الليثيوم والإلكترونات لتكوين نواتج \nمثل Li₂CO₃ وبعض الأنواع الوسيطة (CO2−•, CO(ads), CO2(ads)). \nشكل السطح والعيوب وبيئة الإلكتروليت تؤثر جميعها في مسار التفاعل وطاقات الحواجز.\n\nKey steps (English, schematic):\n1. CO2(g) → CO2(ads) on Hybrid MOF–carbon composite surface.\n2. CO2(ads) + e− + Li+ → LiCO2-like intermediate.\n3. Coupling and further reduction form Li2CO3 and possibly CO-containing species.\n4. During charge, Li2CO3 is decomposed on catalytic sites, releasing CO2 (and sometimes O2).\n\nالخطوات الرئيسية (بالعربية بشكل مبسّط):\n1- امتصاص CO₂ من الطور الغازي على سطح مركب هجين من MOF مع الكربون.\n2- انتقال الإلكترونات وأيونات Li⁺ لتكوين نوع وسيط مشابه لـ LiCO₂.\n3- تَحوُّل الأنواع الوسيطة إلى Li₂CO₃ ونواتج أخرى حاوية على الكربون.\n4- في الشحن، يساعد السطح التحفيزي على تفكيك Li₂CO₃ وإعادة إطلاق CO₂.\n", "metadata": {"mechanism_id": "M018", "focus_catalyst": "Hybrid MOF–carbon composite", "focus_catalyst_ar": "مركب هجين من MOF مع الكربون", "mechanism_topic_en": "side reactions and by-products", "mechanism_topic_ar": "التفاعلات الجانبية والنواتج الثانوية", "main_intermediates": ["CO2−•", "CO(ads)", "CO2(ads)"], "barrier_range_eV": [0.301, 0.569], "overpotential_trend": "Moderately reduced vs. pure carbon", "evidence_type": ["DFT-style analysis (synthetic)", "Conceptual mechanism"], "chunk_type": "mechanism_bilingual"}}
{"text": "Mechanism ID: M019\nTitle: Co/Mn spinel oxide–assisted discharge process in Li–CO2 cells\nالعنوان بالعربية: آلية التفريغ على أكاسيد سبينل الكوبالت/المنغنيز في بطاريات Li–CO₂\n\nEnglish description:\nThis mechanism describes how Co/Mn spinel oxide participates in the discharge process of a Li–CO2 battery. \nCO2 from the gas phase is adsorbed on the catalytic surface, reacts with Li+ and electrons, \nand forms solid discharge products such as Li2CO3 together with other intermediates \n(Li2C2O4, CO(ads), CO2(ads)). The exact pathway and energy barriers depend on the catalyst surface, \ndefect density, and the local electrolyte environment.\n\nالوصف بالعربية (مختصر):\nتشرح هذه الآلية كيف يساهم أكاسيد سبينل الكوبالت/المنغنيز في آلية التفريغ داخل خلية Li–CO₂. \nيُمتص غاز CO₂ على السطح النشط، ثم يتفاعل مع أيونات الليثيوم والإلكترونات لتكوين نواتج \nمثل Li₂CO₃ وبعض الأنواع الوسيطة (Li2C2O4, CO(ads), CO2(ads)). \nشكل السطح والعيوب وبيئة الإلكتروليت تؤثر جميعها في مسار التفاعل وطاقات الحواجز.\n\nKey steps (English, schematic):\n1. CO2(g) → CO2(ads) on Co/Mn spinel oxide surface.\n2. CO2(ads) + e− + Li+ → LiCO2-like intermediate.\n3. Coupling and further reduction form Li2CO3 and possibly CO-containing species.\n4. During charge, Li2CO3 is decomposed on catalytic sites, releasing CO2 (and sometimes O2).\n\nالخطوات الرئيسية (بالعربية بشكل مبسّط):\n1- امتصاص CO₂ من الطور الغازي على سطح أكاسيد سبينل الكوبالت/المنغنيز.\n2- انتقال الإلكترونات وأيونات Li⁺ لتكوين نوع وسيط مشابه لـ LiCO₂.\n3- تَحوُّل الأنواع الوسيطة إلى Li₂CO₃ ونواتج أخرى حاوية على الكربون.\n4- في الشحن، يساعد السطح التحفيزي على تفكيك Li₂CO₃ وإعادة إطلاق CO₂.\n", "metadata": {"mechanism_id": "M019", "focus_catalyst": "Co/Mn spinel oxide", "focus_catalyst_ar": "أكاسيد سبينل الكوبالت/المنغنيز", "mechanism_topic_en": "discharge process", "mechanism_topic_ar": "آلية التفريغ", "main_intermediates": ["Li2C2O4", "CO(ads)", "CO2(ads)"], "barrier_range_eV": [0.284, 0.615], "overpotential_trend": "Significantly reduced when catalyst is well dispersed", "evidence_type": ["DFT-style analysis (synthetic)", "Conceptual mechanism"], "chunk_type": "mechanism_bilingual"}}
{"text": "Mechanism ID: M020\nTitle: Mo2C carbide–assisted charge process in Li–CO2 cells\nالعنوان بالعربية: آلية الشحن على كربيد الموليبدينوم Mo₂C في بطاريات Li–CO₂\n\nEnglish description:\nThis mechanism describes how Mo2C carbide participates in the charge process of a Li–CO2 battery. \nCO2 from the gas phase is adsorbed on the catalytic surface, reacts with Li+ and electrons, \nand forms solid discharge products such as Li2CO3 together with other intermediates \n(Li2C2O4, Li2CO3, CO2−•, Li2O). The exact pathway and energy barriers depend on the catalyst surface, \ndefect density, and the local electrolyte environment.\n\nالوصف بالعربية (مختصر):\nتشرح هذه الآلية كيف يساهم كربيد الموليبدينوم Mo₂C في آلية الشحن داخل خلية Li–CO₂. \nيُمتص غاز CO₂ على السطح النشط، ثم يتفاعل مع أيونات الليثيوم والإلكترونات لتكوين نواتج \nمثل Li₂CO₃ وبعض الأنواع الوسيطة (Li2C2O4, Li2CO3, CO2−•, Li2O). \nشكل السطح والعيوب وبيئة الإلكتروليت تؤثر جميعها في مسار التفاعل وطاقات الحواجز.\n\nKey steps (English, schematic):\n1. CO2(g) → CO2(ads) on Mo2C carbide surface.\n2. CO2(ads) + e− + Li+ → LiCO2-like intermediate.\n3. Coupling and further reduction form Li2CO3 and possibly CO-containing species.\n4. During charge, Li2CO3 is decomposed on catalytic sites, releasing CO2 (and sometimes O2).\n\nالخطوات الرئيسية (بالعربية بشكل مبسّط):\n1- امتصاص CO₂ من الطور الغازي على سطح كربيد الموليبدينوم Mo₂C.\n2- انتقال الإلكترونات وأيونات Li⁺ لتكوين نوع وسيط مشابه لـ LiCO₂.\n3- تَحوُّل الأنواع الوسيطة إلى Li₂CO₃ ونواتج أخرى حاوية على الكربون.\n4- في الشحن، يساعد السطح التحفيزي على تفكيك Li₂CO₃ وإعادة إطلاق CO₂.\n", "metadata": {"mechanism_id": "M020", "focus_catalyst": "Mo2C carbide", "focus_catalyst_ar": "كربيد الموليبدينوم Mo₂C", "mechanism_topic_en": "charge process", "mechanism_topic_ar": "آلية الشحن", "main_intermediates": ["Li2C2O4", "Li2CO3", "CO2−•", "Li2O"], "barrier_range_eV": [0.359, 0.685], "overpotential_trend": "Sensitive to Li2CO3 film morphology", "evidence_type": ["DFT-style analysis (synthetic)", "Conceptual mechanism"], "chunk_type": "mechanism_bilingual"}}
{"text": "Mechanism ID: M021\nTitle: Co/Mn spinel oxide–assisted side reactions and by-products in Li–CO2 cells\nالعنوان بالعربية: التفاعلات الجانبية والنواتج الثانوية على أكاسيد سبينل الكوبالت/المنغنيز في بطاريات Li–CO₂\n\nEnglish description:\nThis mechanism describes how Co/Mn spinel oxide participates in the side reactions and by-products of a Li–CO2 battery. \nCO2 from the gas phase is adsorbed on the catalytic surface, reacts with Li+ and electrons, \nand forms solid discharge products such as Li2CO3 together with other intermediates \n(CO2−•, CO2(ads), Li2C2O4, Li2CO3). The exact pathway and energy barriers depend on the catalyst surface, \ndefect density, and the local electrolyte environment.\n\nالوصف بالعربية (مختصر):\nتشرح هذه الآلية كيف يساهم أكاسيد سبينل الكوبالت/المنغنيز في التفاعلات الجانبية والنواتج الثانوية داخل خلية Li–CO₂. \nيُمتص غاز CO₂ على السطح النشط، ثم يتفاعل مع أيونات الليثيوم والإلكترونات لتكوين نواتج \nمثل Li₂CO₃ وبعض الأنواع الوسيطة (CO2−•, CO2(ads), Li2C2O4, Li2CO3). \nشكل السطح والعيوب وبيئة الإلكتروليت تؤثر جميعها في مسار التفاعل وطاقات الحواجز.\n\nKey steps (English, schematic):\n1. CO2(g) → CO2(ads) on Co/Mn spinel oxide surface.\n2. CO2(ads) + e− + Li+ → LiCO2-like intermediate.\n3. Coupling and further reduction form Li2CO3 and possibly CO-containing species.\n4. During charge, Li2CO3 is decomposed on catalytic sites, releasing CO2 (and sometimes O2).\n\nالخطوات الرئيسية (بالعربية بشكل مبسّط):\n1- امتصاص CO₂ من الطور الغازي على سطح أكاسيد سبينل الكوبالت/المنغنيز.\n2- انتقال الإلكترونات وأيونات Li⁺ لتكوين نوع وسيط مشابه لـ LiCO₂.\n3- تَحوُّل الأنواع الوسيطة إلى Li₂CO₃ ونواتج أخرى حاوية على الكربون.\n4- في الشحن، يساعد السطح التحفيزي على تفكيك Li₂CO₃ وإعادة إطلاق CO₂.\n", "metadata": {"mechanism_id": "M021", "focus_catalyst": "Co/Mn spinel oxide", "focus_catalyst_ar": "أكاسيد سبينل الكوبالت/المنغنيز", "mechanism_topic_en": "side reactions and by-products", "mechanism_topic_ar": "التفاعلات الجانبية والنواتج الثانوية", "main_intermediates": ["CO2−•", "CO2(ads)", "Li2C2O4", "Li2CO3"], "barrier_range_eV": [0.303, 0.535], "overpotential_trend": "High during charge, moderate during discharge", "evidence_type": ["DFT-style analysis (synthetic)", "Conceptual mechanism"], "chunk_type": "mechanism_bilingual"}}
{"text": "Mechanism ID: M022\nTitle: Mo2C carbide–assisted discharge process in Li–CO2 cells\nالعنوان بالعربية: آلية التفريغ على كربيد الموليبدينوم Mo₂C في بطاريات Li–CO₂\n\nEnglish description:\nThis mechanism describes how Mo2C carbide participates in the discharge process of a Li–CO2 battery. \nCO2 from the gas phase is adsorbed on the catalytic surface, reacts with Li+ and electrons, \nand forms solid discharge products such as Li2CO3 together with other intermediates \n(Li2C2O4, LiCO2, CO2(ads), CO2−•). The exact pathway and energy barriers depend on the catalyst surface, \ndefect density, and the local electrolyte environment.\n\nالوصف بالعربية (مختصر):\nتشرح هذه الآلية كيف يساهم كربيد الموليبدينوم Mo₂C في آلية التفريغ داخل خلية Li–CO₂. \nيُمتص غاز CO₂ على السطح النشط، ثم يتفاعل مع أيونات الليثيوم والإلكترونات لتكوين نواتج \nمثل Li₂CO₃ وبعض الأنواع الوسيطة (Li2C2O4, LiCO2, CO2(ads), CO2−•). \nشكل السطح والعيوب وبيئة الإلكتروليت تؤثر جميعها في مسار التفاعل وطاقات الحواجز.\n\nKey steps (English, schematic):\n1. CO2(g) → CO2(ads) on Mo2C carbide surface.\n2. CO2(ads) + e− + Li+ → LiCO2-like intermediate.\n3. Coupling and further reduction form Li2CO3 and possibly CO-containing species.\n4. During charge, Li2CO3 is decomposed on catalytic sites, releasing CO2 (and sometimes O2).\n\nالخطوات الرئيسية (بالعربية بشكل مبسّط):\n1- امتصاص CO₂ من الطور الغازي على سطح كربيد الموليبدينوم Mo₂C.\n2- انتقال الإلكترونات وأيونات Li⁺ لتكوين نوع وسيط مشابه لـ LiCO₂.\n3- تَحوُّل الأنواع الوسيطة إلى Li₂CO₃ ونواتج أخرى حاوية على الكربون.\n4- في الشحن، يساعد السطح التحفيزي على تفكيك Li₂CO₃ وإعادة إطلاق CO₂.\n", "metadata": {"mechanism_id": "M022", "focus_catalyst": "Mo2C carbide", "focus_catalyst_ar": "كربيد الموليبدينوم Mo₂C", "mechanism_topic_en": "discharge process", "mechanism_topic_ar": "آلية التفريغ", "main_intermediates": ["Li2C2O4", "LiCO2", "CO2(ads)", "CO2−•"], "barrier_range_eV": [0.279, 0.536], "overpotential_trend": "Moderately reduced vs. pure carbon", "evidence_type": ["DFT-style analysis (synthetic)", "Conceptual mechanism"], "chunk_type": "mechanism_bilingual"}}
{"text": "Mechanism ID: M023\nTitle: COF host with N-doped linkers–assisted charge process in Li–CO2 cells\nالعنوان بالعربية: آلية الشحن على إطار عضوي تساهمي بروابط غنية بالنيتروجين في بطاريات Li–CO₂\n\nEnglish description:\nThis mechanism describes how COF host with N-doped linkers participates in the charge process of a Li–CO2 battery. \nCO2 from the gas phase is adsorbed on the catalytic surface, reacts with Li+ and electrons, \nand forms solid discharge products such as Li2CO3 together with other intermediates \n(Li2CO3, CO2−•, CO2(ads), CO(ads)). The exact pathway and energy barriers depend on the catalyst surface, \ndefect density, and the local electrolyte environment.\n\nالوصف بالعربية (مختصر):\nتشرح هذه الآلية كيف يساهم إطار عضوي تساهمي بروابط غنية بالنيتروجين في آلية الشحن داخل خلية Li–CO₂. \nيُمتص غاز CO₂ على السطح النشط، ثم يتفاعل مع أيونات الليثيوم والإلكترونات لتكوين نواتج \nمثل Li₂CO₃ وبعض الأنواع الوسيطة (Li2CO3, CO2−•, CO2(ads), CO(ads)). \nشكل السطح والعيوب وبيئة الإلكتروليت تؤثر جميعها في مسار التفاعل وطاقات الحواجز.\n\nKey steps (English, schematic):\n1. CO2(g) → CO2(ads) on COF host with N-doped linkers surface.\n2. CO2(ads) + e− + Li+ → LiCO2-like intermediate.\n3. Coupling and further reduction form Li2CO3 and possibly CO-containing species.\n4. During charge, Li2CO3 is decomposed on catalytic sites, releasing CO2 (and sometimes O2).\n\nالخطوات الرئيسية (بالعربية بشكل مبسّط):\n1- امتصاص CO₂ من الطور الغازي على سطح إطار عضوي تساهمي بروابط غنية بالنيتروجين.\n2- انتقال الإلكترونات وأيونات Li⁺ لتكوين نوع وسيط مشابه لـ LiCO₂.\n3- تَحوُّل الأنواع الوسيطة إلى Li₂CO₃ ونواتج أخرى حاوية على الكربون.\n4- في الشحن، يساعد السطح التحفيزي على تفكيك Li₂CO₃ وإعادة إطلاق CO₂.\n", "metadata": {"mechanism_id": "M023", "focus_catalyst": "COF host with N-doped linkers", "focus_catalyst_ar": "إطار عضوي تساهمي بروابط غنية بالنيتروجين", "mechanism_topic_en": "charge process", "mechanism_topic_ar": "آلية الشحن", "main_intermediates": ["Li2CO3", "CO2−•", "CO2(ads)", "CO(ads)"], "barrier_range_eV": [0.371, 0.692], "overpotential_trend": "High during charge, moderate during discharge", "evidence_type": ["DFT-style analysis (synthetic)", "Conceptual mechanism"], "chunk_type": "mechanism_bilingual"}}
{"text": "Mechanism ID: M024\nTitle: Porous carbon–assisted discharge process in Li–CO2 cells\nالعنوان بالعربية: آلية التفريغ على الكربون المسامي في بطاريات Li–CO₂\n\nEnglish description:\nThis mechanism describes how Porous carbon participates in the discharge process of a Li–CO2 battery. \nCO2 from the gas phase is adsorbed on the catalytic surface, reacts with Li+ and electrons, \nand forms solid discharge products such as Li2CO3 together with other intermediates \n(CO(ads), CO2−•, Li2C2O4). The exact pathway and energy barriers depend on the catalyst surface, \ndefect density, and the local electrolyte environment.\n\nالوصف بالعربية (مختصر):\nتشرح هذه الآلية كيف يساهم الكربون المسامي في آلية التفريغ داخل خلية Li–CO₂. \nيُمتص غاز CO₂ على السطح النشط، ثم يتفاعل مع أيونات الليثيوم والإلكترونات لتكوين نواتج \nمثل Li₂CO₃ وبعض الأنواع الوسيطة (CO(ads), CO2−•, Li2C2O4). \nشكل السطح والعيوب وبيئة الإلكتروليت تؤثر جميعها في مسار التفاعل وطاقات الحواجز.\n\nKey steps (English, schematic):\n1. CO2(g) → CO2(ads) on Porous carbon surface.\n2. CO2(ads) + e− + Li+ → LiCO2-like intermediate.\n3. Coupling and further reduction form Li2CO3 and possibly CO-containing species.\n4. During charge, Li2CO3 is decomposed on catalytic sites, releasing CO2 (and sometimes O2).\n\nالخطوات الرئيسية (بالعربية بشكل مبسّط):\n1- امتصاص CO₂ من الطور الغازي على سطح الكربون المسامي.\n2- انتقال الإلكترونات وأيونات Li⁺ لتكوين نوع وسيط مشابه لـ LiCO₂.\n3- تَحوُّل الأنواع الوسيطة إلى Li₂CO₃ ونواتج أخرى حاوية على الكربون.\n4- في الشحن، يساعد السطح التحفيزي على تفكيك Li₂CO₃ وإعادة إطلاق CO₂.\n", "metadata": {"mechanism_id": "M024", "focus_catalyst": "Porous carbon", "focus_catalyst_ar": "الكربون المسامي", "mechanism_topic_en": "discharge process", "mechanism_topic_ar": "آلية التفريغ", "main_intermediates": ["CO(ads)", "CO2−•", "Li2C2O4"], "barrier_range_eV": [0.311, 0.557], "overpotential_trend": "Sensitive to Li2CO3 film morphology", "evidence_type": ["DFT-style analysis (synthetic)", "Conceptual mechanism"], "chunk_type": "mechanism_bilingual"}}
{"text": "Mechanism ID: M025\nTitle: Porous carbon–assisted charge process in Li–CO2 cells\nالعنوان بالعربية: آلية الشحن على الكربون المسامي في بطاريات Li–CO₂\n\nEnglish description:\nThis mechanism describes how Porous carbon participates in the charge process of a Li–CO2 battery. \nCO2 from the gas phase is adsorbed on the catalytic surface, reacts with Li+ and electrons, \nand forms solid discharge products such as Li2CO3 together with other intermediates \n(CO2(ads), Li2CO3, LiCO2, Li2C2O4). The exact pathway and energy barriers depend on the catalyst surface, \ndefect density, and the local electrolyte environment.\n\nالوصف بالعربية (مختصر):\nتشرح هذه الآلية كيف يساهم الكربون المسامي في آلية الشحن داخل خلية Li–CO₂. \nيُمتص غاز CO₂ على السطح النشط، ثم يتفاعل مع أيونات الليثيوم والإلكترونات لتكوين نواتج \nمثل Li₂CO₃ وبعض الأنواع الوسيطة (CO2(ads), Li2CO3, LiCO2, Li2C2O4). \nشكل السطح والعيوب وبيئة الإلكتروليت تؤثر جميعها في مسار التفاعل وطاقات الحواجز.\n\nKey steps (English, schematic):\n1. CO2(g) → CO2(ads) on Porous carbon surface.\n2. CO2(ads) + e− + Li+ → LiCO2-like intermediate.\n3. Coupling and further reduction form Li2CO3 and possibly CO-containing species.\n4. During charge, Li2CO3 is decomposed on catalytic sites, releasing CO2 (and sometimes O2).\n\nالخطوات الرئيسية (بالعربية بشكل مبسّط):\n1- امتصاص CO₂ من الطور الغازي على سطح الكربون المسامي.\n2- انتقال الإلكترونات وأيونات Li⁺ لتكوين نوع وسيط مشابه لـ LiCO₂.\n3- تَحوُّل الأنواع الوسيطة إلى Li₂CO₃ ونواتج أخرى حاوية على الكربون.\n4- في الشحن، يساعد السطح التحفيزي على تفكيك Li₂CO₃ وإعادة إطلاق CO₂.\n", "metadata": {"mechanism_id": "M025", "focus_catalyst": "Porous carbon", "focus_catalyst_ar": "الكربون المسامي", "mechanism_topic_en": "charge process", "mechanism_topic_ar": "آلية الشحن", "main_intermediates": ["CO2(ads)", "Li2CO3", "LiCO2", "Li2C2O4"], "barrier_range_eV": [0.293, 0.582], "overpotential_trend": "Sensitive to Li2CO3 film morphology", "evidence_type": ["DFT-style analysis (synthetic)", "Conceptual mechanism"], "chunk_type": "mechanism_bilingual"}}
{"text": "Mechanism ID: M026\nTitle: Ru single-atom sites–assisted charge process in Li–CO2 cells\nالعنوان بالعربية: آلية الشحن على مواقع الروثينيوم أحادي الذرة في بطاريات Li–CO₂\n\nEnglish description:\nThis mechanism describes how Ru single-atom sites participates in the charge process of a Li–CO2 battery. \nCO2 from the gas phase is adsorbed on the catalytic surface, reacts with Li+ and electrons, \nand forms solid discharge products such as Li2CO3 together with other intermediates \n(CO2−•, CO2(ads), Li2O, Li2C2O4). The exact pathway and energy barriers depend on the catalyst surface, \ndefect density, and the local electrolyte environment.\n\nالوصف بالعربية (مختصر):\nتشرح هذه الآلية كيف يساهم مواقع الروثينيوم أحادي الذرة في آلية الشحن داخل خلية Li–CO₂. \nيُمتص غاز CO₂ على السطح النشط، ثم يتفاعل مع أيونات الليثيوم والإلكترونات لتكوين نواتج \nمثل Li₂CO₃ وبعض الأنواع الوسيطة (CO2−•, CO2(ads), Li2O, Li2C2O4). \nشكل السطح والعيوب وبيئة الإلكتروليت تؤثر جميعها في مسار التفاعل وطاقات الحواجز.\n\nKey steps (English, schematic):\n1. CO2(g) → CO2(ads) on Ru single-atom sites surface.\n2. CO2(ads) + e− + Li+ → LiCO2-like intermediate.\n3. Coupling and further reduction form Li2CO3 and possibly CO-containing species.\n4. During charge, Li2CO3 is decomposed on catalytic sites, releasing CO2 (and sometimes O2).\n\nالخطوات الرئيسية (بالعربية بشكل مبسّط):\n1- امتصاص CO₂ من الطور الغازي على سطح مواقع الروثينيوم أحادي الذرة.\n2- انتقال الإلكترونات وأيونات Li⁺ لتكوين نوع وسيط مشابه لـ LiCO₂.\n3- تَحوُّل الأنواع الوسيطة إلى Li₂CO₃ ونواتج أخرى حاوية على الكربون.\n4- في الشحن، يساعد السطح التحفيزي على تفكيك Li₂CO₃ وإعادة إطلاق CO₂.\n", "metadata": {"mechanism_id": "M026", "focus_catalyst": "Ru single-atom sites", "focus_catalyst_ar": "مواقع الروثينيوم أحادي الذرة", "mechanism_topic_en": "charge process", "mechanism_topic_ar": "آلية الشحن", "main_intermediates": ["CO2−•", "CO2(ads)", "Li2O", "Li2C2O4"], "barrier_range_eV": [0.362, 0.523], "overpotential_trend": "Sensitive to Li2CO3 film morphology", "evidence_type": ["DFT-style analysis (synthetic)", "Conceptual mechanism"], "chunk_type": "mechanism_bilingual"}}
{"text": "Mechanism ID: M027\nTitle: Ru single-atom sites–assisted discharge process in Li–CO2 cells\nالعنوان بالعربية: آلية التفريغ على مواقع الروثينيوم أحادي الذرة في بطاريات Li–CO₂\n\nEnglish description:\nThis mechanism describes how Ru single-atom sites participates in the discharge process of a Li–CO2 battery. \nCO2 from the gas phase is adsorbed on the catalytic surface, reacts with Li+ and electrons, \nand forms solid discharge products such as Li2CO3 together with other intermediates \n(CO2(ads), CO2−•, CO(ads), Li2O, LiCO2). The exact pathway and energy barriers depend on the catalyst surface, \ndefect density, and the local electrolyte environment.\n\nالوصف بالعربية (مختصر):\nتشرح هذه الآلية كيف يساهم مواقع الروثينيوم أحادي الذرة في آلية التفريغ داخل خلية Li–CO₂. \nيُمتص غاز CO₂ على السطح النشط، ثم يتفاعل مع أيونات الليثيوم والإلكترونات لتكوين نواتج \nمثل Li₂CO₃ وبعض الأنواع الوسيطة (CO2(ads), CO2−•, CO(ads), Li2O, LiCO2). \nشكل السطح والعيوب وبيئة الإلكتروليت تؤثر جميعها في مسار التفاعل وطاقات الحواجز.\n\nKey steps (English, schematic):\n1. CO2(g) → CO2(ads) on Ru single-atom sites surface.\n2. CO2(ads) + e− + Li+ → LiCO2-like intermediate.\n3. Coupling and further reduction form Li2CO3 and possibly CO-containing species.\n4. During charge, Li2CO3 is decomposed on catalytic sites, releasing CO2 (and sometimes O2).\n\nالخطوات الرئيسية (بالعربية بشكل مبسّط):\n1- امتصاص CO₂ من الطور الغازي على سطح مواقع الروثينيوم أحادي الذرة.\n2- انتقال الإلكترونات وأيونات Li⁺ لتكوين نوع وسيط مشابه لـ LiCO₂.\n3- تَحوُّل الأنواع الوسيطة إلى Li₂CO₃ ونواتج أخرى حاوية على الكربون.\n4- في الشحن، يساعد السطح التحفيزي على تفكيك Li₂CO₃ وإعادة إطلاق CO₂.\n", "metadata": {"mechanism_id": "M027", "focus_catalyst": "Ru single-atom sites", "focus_catalyst_ar": "مواقع الروثينيوم أحادي الذرة", "mechanism_topic_en": "discharge process", "mechanism_topic_ar": "آلية التفريغ", "main_intermediates": ["CO2(ads)", "CO2−•", "CO(ads)", "Li2O", "LiCO2"], "barrier_range_eV": [0.379, 0.61], "overpotential_trend": "Moderately reduced vs. pure carbon", "evidence_type": ["DFT-style analysis (synthetic)", "Conceptual mechanism"], "chunk_type": "mechanism_bilingual"}}
{"text": "Mechanism ID: M028\nTitle: Porous carbon–assisted discharge process in Li–CO2 cells\nالعنوان بالعربية: آلية التفريغ على الكربون المسامي في بطاريات Li–CO₂\n\nEnglish description:\nThis mechanism describes how Porous carbon participates in the discharge process of a Li–CO2 battery. \nCO2 from the gas phase is adsorbed on the catalytic surface, reacts with Li+ and electrons, \nand forms solid discharge products such as Li2CO3 together with other intermediates \n(Li2C2O4, Li2O, CO(ads), LiCO2). The exact pathway and energy barriers depend on the catalyst surface, \ndefect density, and the local electrolyte environment.\n\nالوصف بالعربية (مختصر):\nتشرح هذه الآلية كيف يساهم الكربون المسامي في آلية التفريغ داخل خلية Li–CO₂. \nيُمتص غاز CO₂ على السطح النشط، ثم يتفاعل مع أيونات الليثيوم والإلكترونات لتكوين نواتج \nمثل Li₂CO₃ وبعض الأنواع الوسيطة (Li2C2O4, Li2O, CO(ads), LiCO2). \nشكل السطح والعيوب وبيئة الإلكتروليت تؤثر جميعها في مسار التفاعل وطاقات الحواجز.\n\nKey steps (English, schematic):\n1. CO2(g) → CO2(ads) on Porous carbon surface.\n2. CO2(ads) + e− + Li+ → LiCO2-like intermediate.\n3. Coupling and further reduction form Li2CO3 and possibly CO-containing species.\n4. During charge, Li2CO3 is decomposed on catalytic sites, releasing CO2 (and sometimes O2).\n\nالخطوات الرئيسية (بالعربية بشكل مبسّط):\n1- امتصاص CO₂ من الطور الغازي على سطح الكربون المسامي.\n2- انتقال الإلكترونات وأيونات Li⁺ لتكوين نوع وسيط مشابه لـ LiCO₂.\n3- تَحوُّل الأنواع الوسيطة إلى Li₂CO₃ ونواتج أخرى حاوية على الكربون.\n4- في الشحن، يساعد السطح التحفيزي على تفكيك Li₂CO₃ وإعادة إطلاق CO₂.\n", "metadata": {"mechanism_id": "M028", "focus_catalyst": "Porous carbon", "focus_catalyst_ar": "الكربون المسامي", "mechanism_topic_en": "discharge process", "mechanism_topic_ar": "آلية التفريغ", "main_intermediates": ["Li2C2O4", "Li2O", "CO(ads)", "LiCO2"], "barrier_range_eV": [0.39, 0.581], "overpotential_trend": "Significantly reduced when catalyst is well dispersed", "evidence_type": ["DFT-style analysis (synthetic)", "Conceptual mechanism"], "chunk_type": "mechanism_bilingual"}}
{"text": "Mechanism ID: M029\nTitle: Co/Mn spinel oxide–assisted full Li–CO2 cycle in Li–CO2 cells\nالعنوان بالعربية: الدورة الكاملة في خلية Li–CO₂ على أكاسيد سبينل الكوبالت/المنغنيز في بطاريات Li–CO₂\n\nEnglish description:\nThis mechanism describes how Co/Mn spinel oxide participates in the full Li–CO2 cycle of a Li–CO2 battery. \nCO2 from the gas phase is adsorbed on the catalytic surface, reacts with Li+ and electrons, \nand forms solid discharge products such as Li2CO3 together with other intermediates \n(CO2−•, Li2C2O4, LiCO2, Li2CO3). The exact pathway and energy barriers depend on the catalyst surface, \ndefect density, and the local electrolyte environment.\n\nالوصف بالعربية (مختصر):\nتشرح هذه الآلية كيف يساهم أكاسيد سبينل الكوبالت/المنغنيز في الدورة الكاملة في خلية Li–CO₂ داخل خلية Li–CO₂. \nيُمتص غاز CO₂ على السطح النشط، ثم يتفاعل مع أيونات الليثيوم والإلكترونات لتكوين نواتج \nمثل Li₂CO₃ وبعض الأنواع الوسيطة (CO2−•, Li2C2O4, LiCO2, Li2CO3). \nشكل السطح والعيوب وبيئة الإلكتروليت تؤثر جميعها في مسار التفاعل وطاقات الحواجز.\n\nKey steps (English, schematic):\n1. CO2(g) → CO2(ads) on Co/Mn spinel oxide surface.\n2. CO2(ads) + e− + Li+ → LiCO2-like intermediate.\n3. Coupling and further reduction form Li2CO3 and possibly CO-containing species.\n4. During charge, Li2CO3 is decomposed on catalytic sites, releasing CO2 (and sometimes O2).\n\nالخطوات الرئيسية (بالعربية بشكل مبسّط):\n1- امتصاص CO₂ من الطور الغازي على سطح أكاسيد سبينل الكوبالت/المنغنيز.\n2- انتقال الإلكترونات وأيونات Li⁺ لتكوين نوع وسيط مشابه لـ LiCO₂.\n3- تَحوُّل الأنواع الوسيطة إلى Li₂CO₃ ونواتج أخرى حاوية على الكربون.\n4- في الشحن، يساعد السطح التحفيزي على تفكيك Li₂CO₃ وإعادة إطلاق CO₂.\n", "metadata": {"mechanism_id": "M029", "focus_catalyst": "Co/Mn spinel oxide", "focus_catalyst_ar": "أكاسيد سبينل الكوبالت/المنغنيز", "mechanism_topic_en": "full Li–CO2 cycle", "mechanism_topic_ar": "الدورة الكاملة في خلية Li–CO₂", "main_intermediates": ["CO2−•", "Li2C2O4", "LiCO2", "Li2CO3"], "barrier_range_eV": [0.297, 0.597], "overpotential_trend": "High during charge, moderate during discharge", "evidence_type": ["DFT-style analysis (synthetic)", "Conceptual mechanism"], "chunk_type": "mechanism_bilingual"}}
{"text": "Mechanism ID: M030\nTitle: Porous carbon–assisted side reactions and by-products in Li–CO2 cells\nالعنوان بالعربية: التفاعلات الجانبية والنواتج الثانوية على الكربون المسامي في بطاريات Li–CO₂\n\nEnglish description:\nThis mechanism describes how Porous carbon participates in the side reactions and by-products of a Li–CO2 battery. \nCO2 from the gas phase is adsorbed on the catalytic surface, reacts with Li+ and electrons, \nand forms solid discharge products such as Li2CO3 together with other intermediates \n(Li2O, CO2(ads), Li2C2O4, CO2−•, LiCO2). The exact pathway and energy barriers depend on the catalyst surface, \ndefect density, and the local electrolyte environment.\n\nالوصف بالعربية (مختصر):\nتشرح هذه الآلية كيف يساهم الكربون المسامي في التفاعلات الجانبية والنواتج الثانوية داخل خلية Li–CO₂. \nيُمتص غاز CO₂ على السطح النشط، ثم يتفاعل مع أيونات الليثيوم والإلكترونات لتكوين نواتج \nمثل Li₂CO₃ وبعض الأنواع الوسيطة (Li2O, CO2(ads), Li2C2O4, CO2−•, LiCO2). \nشكل السطح والعيوب وبيئة الإلكتروليت تؤثر جميعها في مسار التفاعل وطاقات الحواجز.\n\nKey steps (English, schematic):\n1. CO2(g) → CO2(ads) on Porous carbon surface.\n2. CO2(ads) + e− + Li+ → LiCO2-like intermediate.\n3. Coupling and further reduction form Li2CO3 and possibly CO-containing species.\n4. During charge, Li2CO3 is decomposed on catalytic sites, releasing CO2 (and sometimes O2).\n\nالخطوات الرئيسية (بالعربية بشكل مبسّط):\n1- امتصاص CO₂ من الطور الغازي على سطح الكربون المسامي.\n2- انتقال الإلكترونات وأيونات Li⁺ لتكوين نوع وسيط مشابه لـ LiCO₂.\n3- تَحوُّل الأنواع الوسيطة إلى Li₂CO₃ ونواتج أخرى حاوية على الكربون.\n4- في الشحن، يساعد السطح التحفيزي على تفكيك Li₂CO₃ وإعادة إطلاق CO₂.\n", "metadata": {"mechanism_id": "M030", "focus_catalyst": "Porous carbon", "focus_catalyst_ar": "الكربون المسامي", "mechanism_topic_en": "side reactions and by-products", "mechanism_topic_ar": "التفاعلات الجانبية والنواتج الثانوية", "main_intermediates": ["Li2O", "CO2(ads)", "Li2C2O4", "CO2−•", "LiCO2"], "barrier_range_eV": [0.29, 0.627], "overpotential_trend": "High during charge, moderate during discharge", "evidence_type": ["DFT-style analysis (synthetic)", "Conceptual mechanism"], "chunk_type": "mechanism_bilingual"}}
{"text": "Mechanism ID: M031\nTitle: Co/Mn spinel oxide–assisted full Li–CO2 cycle in Li–CO2 cells\nالعنوان بالعربية: الدورة الكاملة في خلية Li–CO₂ على أكاسيد سبينل الكوبالت/المنغنيز في بطاريات Li–CO₂\n\nEnglish description:\nThis mechanism describes how Co/Mn spinel oxide participates in the full Li–CO2 cycle of a Li–CO2 battery. \nCO2 from the gas phase is adsorbed on the catalytic surface, reacts with Li+ and electrons, \nand forms solid discharge products such as Li2CO3 together with other intermediates \n(CO2−•, Li2CO3, Li2O, LiCO2). The exact pathway and energy barriers depend on the catalyst surface, \ndefect density, and the local electrolyte environment.\n\nالوصف بالعربية (مختصر):\nتشرح هذه الآلية كيف يساهم أكاسيد سبينل الكوبالت/المنغنيز في الدورة الكاملة في خلية Li–CO₂ داخل خلية Li–CO₂. \nيُمتص غاز CO₂ على السطح النشط، ثم يتفاعل مع أيونات الليثيوم والإلكترونات لتكوين نواتج \nمثل Li₂CO₃ وبعض الأنواع الوسيطة (CO2−•, Li2CO3, Li2O, LiCO2). \nشكل السطح والعيوب وبيئة الإلكتروليت تؤثر جميعها في مسار التفاعل وطاقات الحواجز.\n\nKey steps (English, schematic):\n1. CO2(g) → CO2(ads) on Co/Mn spinel oxide surface.\n2. CO2(ads) + e− + Li+ → LiCO2-like intermediate.\n3. Coupling and further reduction form Li2CO3 and possibly CO-containing species.\n4. During charge, Li2CO3 is decomposed on catalytic sites, releasing CO2 (and sometimes O2).\n\nالخطوات الرئيسية (بالعربية بشكل مبسّط):\n1- امتصاص CO₂ من الطور الغازي على سطح أكاسيد سبينل الكوبالت/المنغنيز.\n2- انتقال الإلكترونات وأيونات Li⁺ لتكوين نوع وسيط مشابه لـ LiCO₂.\n3- تَحوُّل الأنواع الوسيطة إلى Li₂CO₃ ونواتج أخرى حاوية على الكربون.\n4- في الشحن، يساعد السطح التحفيزي على تفكيك Li₂CO₃ وإعادة إطلاق CO₂.\n", "metadata": {"mechanism_id": "M031", "focus_catalyst": "Co/Mn spinel oxide", "focus_catalyst_ar": "أكاسيد سبينل الكوبالت/المنغنيز", "mechanism_topic_en": "full Li–CO2 cycle", "mechanism_topic_ar": "الدورة الكاملة في خلية Li–CO₂", "main_intermediates": ["CO2−•", "Li2CO3", "Li2O", "LiCO2"], "barrier_range_eV": [0.342, 0.689], "overpotential_trend": "High during charge, moderate during discharge", "evidence_type": ["DFT-style analysis (synthetic)", "Conceptual mechanism"], "chunk_type": "mechanism_bilingual"}}
{"text": "Mechanism ID: M032\nTitle: Ni-rich layered oxide–assisted discharge process in Li–CO2 cells\nالعنوان بالعربية: آلية التفريغ على أكاسيد نيكل طبقية عالية النيكل في بطاريات Li–CO₂\n\nEnglish description:\nThis mechanism describes how Ni-rich layered oxide participates in the discharge process of a Li–CO2 battery. \nCO2 from the gas phase is adsorbed on the catalytic surface, reacts with Li+ and electrons, \nand forms solid discharge products such as Li2CO3 together with other intermediates \n(LiCO2, CO2(ads), Li2C2O4). The exact pathway and energy barriers depend on the catalyst surface, \ndefect density, and the local electrolyte environment.\n\nالوصف بالعربية (مختصر):\nتشرح هذه الآلية كيف يساهم أكاسيد نيكل طبقية عالية النيكل في آلية التفريغ داخل خلية Li–CO₂. \nيُمتص غاز CO₂ على السطح النشط، ثم يتفاعل مع أيونات الليثيوم والإلكترونات لتكوين نواتج \nمثل Li₂CO₃ وبعض الأنواع الوسيطة (LiCO2, CO2(ads), Li2C2O4). \nشكل السطح والعيوب وبيئة الإلكتروليت تؤثر جميعها في مسار التفاعل وطاقات الحواجز.\n\nKey steps (English, schematic):\n1. CO2(g) → CO2(ads) on Ni-rich layered oxide surface.\n2. CO2(ads) + e− + Li+ → LiCO2-like intermediate.\n3. Coupling and further reduction form Li2CO3 and possibly CO-containing species.\n4. During charge, Li2CO3 is decomposed on catalytic sites, releasing CO2 (and sometimes O2).\n\nالخطوات الرئيسية (بالعربية بشكل مبسّط):\n1- امتصاص CO₂ من الطور الغازي على سطح أكاسيد نيكل طبقية عالية النيكل.\n2- انتقال الإلكترونات وأيونات Li⁺ لتكوين نوع وسيط مشابه لـ LiCO₂.\n3- تَحوُّل الأنواع الوسيطة إلى Li₂CO₃ ونواتج أخرى حاوية على الكربون.\n4- في الشحن، يساعد السطح التحفيزي على تفكيك Li₂CO₃ وإعادة إطلاق CO₂.\n", "metadata": {"mechanism_id": "M032", "focus_catalyst": "Ni-rich layered oxide", "focus_catalyst_ar": "أكاسيد نيكل طبقية عالية النيكل", "mechanism_topic_en": "discharge process", "mechanism_topic_ar": "آلية التفريغ", "main_intermediates": ["LiCO2", "CO2(ads)", "Li2C2O4"], "barrier_range_eV": [0.361, 0.542], "overpotential_trend": "Significantly reduced when catalyst is well dispersed", "evidence_type": ["DFT-style analysis (synthetic)", "Conceptual mechanism"], "chunk_type": "mechanism_bilingual"}}
{"text": "Mechanism ID: M033\nTitle: Co/Mn spinel oxide–assisted full Li–CO2 cycle in Li–CO2 cells\nالعنوان بالعربية: الدورة الكاملة في خلية Li–CO₂ على أكاسيد سبينل الكوبالت/المنغنيز في بطاريات Li–CO₂\n\nEnglish description:\nThis mechanism describes how Co/Mn spinel oxide participates in the full Li–CO2 cycle of a Li–CO2 battery. \nCO2 from the gas phase is adsorbed on the catalytic surface, reacts with Li+ and electrons, \nand forms solid discharge products such as Li2CO3 together with other intermediates \n(Li2C2O4, CO(ads), LiCO2). The exact pathway and energy barriers depend on the catalyst surface, \ndefect density, and the local electrolyte environment.\n\nالوصف بالعربية (مختصر):\nتشرح هذه الآلية كيف يساهم أكاسيد سبينل الكوبالت/المنغنيز في الدورة الكاملة في خلية Li–CO₂ داخل خلية Li–CO₂. \nيُمتص غاز CO₂ على السطح النشط، ثم يتفاعل مع أيونات الليثيوم والإلكترونات لتكوين نواتج \nمثل Li₂CO₃ وبعض الأنواع الوسيطة (Li2C2O4, CO(ads), LiCO2). \nشكل السطح والعيوب وبيئة الإلكتروليت تؤثر جميعها في مسار التفاعل وطاقات الحواجز.\n\nKey steps (English, schematic):\n1. CO2(g) → CO2(ads) on Co/Mn spinel oxide surface.\n2. CO2(ads) + e− + Li+ → LiCO2-like intermediate.\n3. Coupling and further reduction form Li2CO3 and possibly CO-containing species.\n4. During charge, Li2CO3 is decomposed on catalytic sites, releasing CO2 (and sometimes O2).\n\nالخطوات الرئيسية (بالعربية بشكل مبسّط):\n1- امتصاص CO₂ من الطور الغازي على سطح أكاسيد سبينل الكوبالت/المنغنيز.\n2- انتقال الإلكترونات وأيونات Li⁺ لتكوين نوع وسيط مشابه لـ LiCO₂.\n3- تَحوُّل الأنواع الوسيطة إلى Li₂CO₃ ونواتج أخرى حاوية على الكربون.\n4- في الشحن، يساعد السطح التحفيزي على تفكيك Li₂CO₃ وإعادة إطلاق CO₂.\n", "metadata": {"mechanism_id": "M033", "focus_catalyst": "Co/Mn spinel oxide", "focus_catalyst_ar": "أكاسيد سبينل الكوبالت/المنغنيز", "mechanism_topic_en": "full Li–CO2 cycle", "mechanism_topic_ar": "الدورة الكاملة في خلية Li–CO₂", "main_intermediates": ["Li2C2O4", "CO(ads)", "LiCO2"], "barrier_range_eV": [0.326, 0.526], "overpotential_trend": "High during charge, moderate during discharge", "evidence_type": ["DFT-style analysis (synthetic)", "Conceptual mechanism"], "chunk_type": "mechanism_bilingual"}}
{"text": "Mechanism ID: M034\nTitle: Mo2C carbide–assisted side reactions and by-products in Li–CO2 cells\nالعنوان بالعربية: التفاعلات الجانبية والنواتج الثانوية على كربيد الموليبدينوم Mo₂C في بطاريات Li–CO₂\n\nEnglish description:\nThis mechanism describes how Mo2C carbide participates in the side reactions and by-products of a Li–CO2 battery. \nCO2 from the gas phase is adsorbed on the catalytic surface, reacts with Li+ and electrons, \nand forms solid discharge products such as Li2CO3 together with other intermediates \n(CO2(ads), CO(ads), LiCO2, CO2−•). The exact pathway and energy barriers depend on the catalyst surface, \ndefect density, and the local electrolyte environment.\n\nالوصف بالعربية (مختصر):\nتشرح هذه الآلية كيف يساهم كربيد الموليبدينوم Mo₂C في التفاعلات الجانبية والنواتج الثانوية داخل خلية Li–CO₂. \nيُمتص غاز CO₂ على السطح النشط، ثم يتفاعل مع أيونات الليثيوم والإلكترونات لتكوين نواتج \nمثل Li₂CO₃ وبعض الأنواع الوسيطة (CO2(ads), CO(ads), LiCO2, CO2−•). \nشكل السطح والعيوب وبيئة الإلكتروليت تؤثر جميعها في مسار التفاعل وطاقات الحواجز.\n\nKey steps (English, schematic):\n1. CO2(g) → CO2(ads) on Mo2C carbide surface.\n2. CO2(ads) + e− + Li+ → LiCO2-like intermediate.\n3. Coupling and further reduction form Li2CO3 and possibly CO-containing species.\n4. During charge, Li2CO3 is decomposed on catalytic sites, releasing CO2 (and sometimes O2).\n\nالخطوات الرئيسية (بالعربية بشكل مبسّط):\n1- امتصاص CO₂ من الطور الغازي على سطح كربيد الموليبدينوم Mo₂C.\n2- انتقال الإلكترونات وأيونات Li⁺ لتكوين نوع وسيط مشابه لـ LiCO₂.\n3- تَحوُّل الأنواع الوسيطة إلى Li₂CO₃ ونواتج أخرى حاوية على الكربون.\n4- في الشحن، يساعد السطح التحفيزي على تفكيك Li₂CO₃ وإعادة إطلاق CO₂.\n", "metadata": {"mechanism_id": "M034", "focus_catalyst": "Mo2C carbide", "focus_catalyst_ar": "كربيد الموليبدينوم Mo₂C", "mechanism_topic_en": "side reactions and by-products", "mechanism_topic_ar": "التفاعلات الجانبية والنواتج الثانوية", "main_intermediates": ["CO2(ads)", "CO(ads)", "LiCO2", "CO2−•"], "barrier_range_eV": [0.346, 0.548], "overpotential_trend": "Sensitive to Li2CO3 film morphology", "evidence_type": ["DFT-style analysis (synthetic)", "Conceptual mechanism"], "chunk_type": "mechanism_bilingual"}}
{"text": "Mechanism ID: M035\nTitle: COF host with N-doped linkers–assisted discharge process in Li–CO2 cells\nالعنوان بالعربية: آلية التفريغ على إطار عضوي تساهمي بروابط غنية بالنيتروجين في بطاريات Li–CO₂\n\nEnglish description:\nThis mechanism describes how COF host with N-doped linkers participates in the discharge process of a Li–CO2 battery. \nCO2 from the gas phase is adsorbed on the catalytic surface, reacts with Li+ and electrons, \nand forms solid discharge products such as Li2CO3 together with other intermediates \n(CO2(ads), Li2C2O4, CO2−•). The exact pathway and energy barriers depend on the catalyst surface, \ndefect density, and the local electrolyte environment.\n\nالوصف بالعربية (مختصر):\nتشرح هذه الآلية كيف يساهم إطار عضوي تساهمي بروابط غنية بالنيتروجين في آلية التفريغ داخل خلية Li–CO₂. \nيُمتص غاز CO₂ على السطح النشط، ثم يتفاعل مع أيونات الليثيوم والإلكترونات لتكوين نواتج \nمثل Li₂CO₃ وبعض الأنواع الوسيطة (CO2(ads), Li2C2O4, CO2−•). \nشكل السطح والعيوب وبيئة الإلكتروليت تؤثر جميعها في مسار التفاعل وطاقات الحواجز.\n\nKey steps (English, schematic):\n1. CO2(g) → CO2(ads) on COF host with N-doped linkers surface.\n2. CO2(ads) + e− + Li+ → LiCO2-like intermediate.\n3. Coupling and further reduction form Li2CO3 and possibly CO-containing species.\n4. During charge, Li2CO3 is decomposed on catalytic sites, releasing CO2 (and sometimes O2).\n\nالخطوات الرئيسية (بالعربية بشكل مبسّط):\n1- امتصاص CO₂ من الطور الغازي على سطح إطار عضوي تساهمي بروابط غنية بالنيتروجين.\n2- انتقال الإلكترونات وأيونات Li⁺ لتكوين نوع وسيط مشابه لـ LiCO₂.\n3- تَحوُّل الأنواع الوسيطة إلى Li₂CO₃ ونواتج أخرى حاوية على الكربون.\n4- في الشحن، يساعد السطح التحفيزي على تفكيك Li₂CO₃ وإعادة إطلاق CO₂.\n", "metadata": {"mechanism_id": "M035", "focus_catalyst": "COF host with N-doped linkers", "focus_catalyst_ar": "إطار عضوي تساهمي بروابط غنية بالنيتروجين", "mechanism_topic_en": "discharge process", "mechanism_topic_ar": "آلية التفريغ", "main_intermediates": ["CO2(ads)", "Li2C2O4", "CO2−•"], "barrier_range_eV": [0.332, 0.649], "overpotential_trend": "Moderately reduced vs. pure carbon", "evidence_type": ["DFT-style analysis (synthetic)", "Conceptual mechanism"], "chunk_type": "mechanism_bilingual"}}
{"text": "Mechanism ID: M036\nTitle: COF host with N-doped linkers–assisted charge process in Li–CO2 cells\nالعنوان بالعربية: آلية الشحن على إطار عضوي تساهمي بروابط غنية بالنيتروجين في بطاريات Li–CO₂\n\nEnglish description:\nThis mechanism describes how COF host with N-doped linkers participates in the charge process of a Li–CO2 battery. \nCO2 from the gas phase is adsorbed on the catalytic surface, reacts with Li+ and electrons, \nand forms solid discharge products such as Li2CO3 together with other intermediates \n(LiCO2, CO(ads), CO2(ads)). The exact pathway and energy barriers depend on the catalyst surface, \ndefect density, and the local electrolyte environment.\n\nالوصف بالعربية (مختصر):\nتشرح هذه الآلية كيف يساهم إطار عضوي تساهمي بروابط غنية بالنيتروجين في آلية الشحن داخل خلية Li–CO₂. \nيُمتص غاز CO₂ على السطح النشط، ثم يتفاعل مع أيونات الليثيوم والإلكترونات لتكوين نواتج \nمثل Li₂CO₃ وبعض الأنواع الوسيطة (LiCO2, CO(ads), CO2(ads)). \nشكل السطح والعيوب وبيئة الإلكتروليت تؤثر جميعها في مسار التفاعل وطاقات الحواجز.\n\nKey steps (English, schematic):\n1. CO2(g) → CO2(ads) on COF host with N-doped linkers surface.\n2. CO2(ads) + e− + Li+ → LiCO2-like intermediate.\n3. Coupling and further reduction form Li2CO3 and possibly CO-containing species.\n4. During charge, Li2CO3 is decomposed on catalytic sites, releasing CO2 (and sometimes O2).\n\nالخطوات الرئيسية (بالعربية بشكل مبسّط):\n1- امتصاص CO₂ من الطور الغازي على سطح إطار عضوي تساهمي بروابط غنية بالنيتروجين.\n2- انتقال الإلكترونات وأيونات Li⁺ لتكوين نوع وسيط مشابه لـ LiCO₂.\n3- تَحوُّل الأنواع الوسيطة إلى Li₂CO₃ ونواتج أخرى حاوية على الكربون.\n4- في الشحن، يساعد السطح التحفيزي على تفكيك Li₂CO₃ وإعادة إطلاق CO₂.\n", "metadata": {"mechanism_id": "M036", "focus_catalyst": "COF host with N-doped linkers", "focus_catalyst_ar": "إطار عضوي تساهمي بروابط غنية بالنيتروجين", "mechanism_topic_en": "charge process", "mechanism_topic_ar": "آلية الشحن", "main_intermediates": ["LiCO2", "CO(ads)", "CO2(ads)"], "barrier_range_eV": [0.385, 0.577], "overpotential_trend": "Moderately reduced vs. pure carbon", "evidence_type": ["DFT-style analysis (synthetic)", "Conceptual mechanism"], "chunk_type": "mechanism_bilingual"}}
{"text": "Mechanism ID: M037\nTitle: Mo2C carbide–assisted full Li–CO2 cycle in Li–CO2 cells\nالعنوان بالعربية: الدورة الكاملة في خلية Li–CO₂ على كربيد الموليبدينوم Mo₂C في بطاريات Li–CO₂\n\nEnglish description:\nThis mechanism describes how Mo2C carbide participates in the full Li–CO2 cycle of a Li–CO2 battery. \nCO2 from the gas phase is adsorbed on the catalytic surface, reacts with Li+ and electrons, \nand forms solid discharge products such as Li2CO3 together with other intermediates \n(CO(ads), Li2CO3, Li2O, CO2−•, CO2(ads)). The exact pathway and energy barriers depend on the catalyst surface, \ndefect density, and the local electrolyte environment.\n\nالوصف بالعربية (مختصر):\nتشرح هذه الآلية كيف يساهم كربيد الموليبدينوم Mo₂C في الدورة الكاملة في خلية Li–CO₂ داخل خلية Li–CO₂. \nيُمتص غاز CO₂ على السطح النشط، ثم يتفاعل مع أيونات الليثيوم والإلكترونات لتكوين نواتج \nمثل Li₂CO₃ وبعض الأنواع الوسيطة (CO(ads), Li2CO3, Li2O, CO2−•, CO2(ads)). \nشكل السطح والعيوب وبيئة الإلكتروليت تؤثر جميعها في مسار التفاعل وطاقات الحواجز.\n\nKey steps (English, schematic):\n1. CO2(g) → CO2(ads) on Mo2C carbide surface.\n2. CO2(ads) + e− + Li+ → LiCO2-like intermediate.\n3. Coupling and further reduction form Li2CO3 and possibly CO-containing species.\n4. During charge, Li2CO3 is decomposed on catalytic sites, releasing CO2 (and sometimes O2).\n\nالخطوات الرئيسية (بالعربية بشكل مبسّط):\n1- امتصاص CO₂ من الطور الغازي على سطح كربيد الموليبدينوم Mo₂C.\n2- انتقال الإلكترونات وأيونات Li⁺ لتكوين نوع وسيط مشابه لـ LiCO₂.\n3- تَحوُّل الأنواع الوسيطة إلى Li₂CO₃ ونواتج أخرى حاوية على الكربون.\n4- في الشحن، يساعد السطح التحفيزي على تفكيك Li₂CO₃ وإعادة إطلاق CO₂.\n", "metadata": {"mechanism_id": "M037", "focus_catalyst": "Mo2C carbide", "focus_catalyst_ar": "كربيد الموليبدينوم Mo₂C", "mechanism_topic_en": "full Li–CO2 cycle", "mechanism_topic_ar": "الدورة الكاملة في خلية Li–CO₂", "main_intermediates": ["CO(ads)", "Li2CO3", "Li2O", "CO2−•", "CO2(ads)"], "barrier_range_eV": [0.38, 0.725], "overpotential_trend": "Moderately reduced vs. pure carbon", "evidence_type": ["DFT-style analysis (synthetic)", "Conceptual mechanism"], "chunk_type": "mechanism_bilingual"}}
{"text": "Mechanism ID: M038\nTitle: COF host with N-doped linkers–assisted discharge process in Li–CO2 cells\nالعنوان بالعربية: آلية التفريغ على إطار عضوي تساهمي بروابط غنية بالنيتروجين في بطاريات Li–CO₂\n\nEnglish description:\nThis mechanism describes how COF host with N-doped linkers participates in the discharge process of a Li–CO2 battery. \nCO2 from the gas phase is adsorbed on the catalytic surface, reacts with Li+ and electrons, \nand forms solid discharge products such as Li2CO3 together with other intermediates \n(Li2C2O4, LiCO2, Li2CO3). The exact pathway and energy barriers depend on the catalyst surface, \ndefect density, and the local electrolyte environment.\n\nالوصف بالعربية (مختصر):\nتشرح هذه الآلية كيف يساهم إطار عضوي تساهمي بروابط غنية بالنيتروجين في آلية التفريغ داخل خلية Li–CO₂. \nيُمتص غاز CO₂ على السطح النشط، ثم يتفاعل مع أيونات الليثيوم والإلكترونات لتكوين نواتج \nمثل Li₂CO₃ وبعض الأنواع الوسيطة (Li2C2O4, LiCO2, Li2CO3). \nشكل السطح والعيوب وبيئة الإلكتروليت تؤثر جميعها في مسار التفاعل وطاقات الحواجز.\n\nKey steps (English, schematic):\n1. CO2(g) → CO2(ads) on COF host with N-doped linkers surface.\n2. CO2(ads) + e− + Li+ → LiCO2-like intermediate.\n3. Coupling and further reduction form Li2CO3 and possibly CO-containing species.\n4. During charge, Li2CO3 is decomposed on catalytic sites, releasing CO2 (and sometimes O2).\n\nالخطوات الرئيسية (بالعربية بشكل مبسّط):\n1- امتصاص CO₂ من الطور الغازي على سطح إطار عضوي تساهمي بروابط غنية بالنيتروجين.\n2- انتقال الإلكترونات وأيونات Li⁺ لتكوين نوع وسيط مشابه لـ LiCO₂.\n3- تَحوُّل الأنواع الوسيطة إلى Li₂CO₃ ونواتج أخرى حاوية على الكربون.\n4- في الشحن، يساعد السطح التحفيزي على تفكيك Li₂CO₃ وإعادة إطلاق CO₂.\n", "metadata": {"mechanism_id": "M038", "focus_catalyst": "COF host with N-doped linkers", "focus_catalyst_ar": "إطار عضوي تساهمي بروابط غنية بالنيتروجين", "mechanism_topic_en": "discharge process", "mechanism_topic_ar": "آلية التفريغ", "main_intermediates": ["Li2C2O4", "LiCO2", "Li2CO3"], "barrier_range_eV": [0.37, 0.693], "overpotential_trend": "Moderately reduced vs. pure carbon", "evidence_type": ["DFT-style analysis (synthetic)", "Conceptual mechanism"], "chunk_type": "mechanism_bilingual"}}
{"text": "Mechanism ID: M039\nTitle: Ni-rich layered oxide–assisted charge process in Li–CO2 cells\nالعنوان بالعربية: آلية الشحن على أكاسيد نيكل طبقية عالية النيكل في بطاريات Li–CO₂\n\nEnglish description:\nThis mechanism describes how Ni-rich layered oxide participates in the charge process of a Li–CO2 battery. \nCO2 from the gas phase is adsorbed on the catalytic surface, reacts with Li+ and electrons, \nand forms solid discharge products such as Li2CO3 together with other intermediates \n(CO2(ads), Li2CO3, CO(ads), Li2C2O4, Li2O). The exact pathway and energy barriers depend on the catalyst surface, \ndefect density, and the local electrolyte environment.\n\nالوصف بالعربية (مختصر):\nتشرح هذه الآلية كيف يساهم أكاسيد نيكل طبقية عالية النيكل في آلية الشحن داخل خلية Li–CO₂. \nيُمتص غاز CO₂ على السطح النشط، ثم يتفاعل مع أيونات الليثيوم والإلكترونات لتكوين نواتج \nمثل Li₂CO₃ وبعض الأنواع الوسيطة (CO2(ads), Li2CO3, CO(ads), Li2C2O4, Li2O). \nشكل السطح والعيوب وبيئة الإلكتروليت تؤثر جميعها في مسار التفاعل وطاقات الحواجز.\n\nKey steps (English, schematic):\n1. CO2(g) → CO2(ads) on Ni-rich layered oxide surface.\n2. CO2(ads) + e− + Li+ → LiCO2-like intermediate.\n3. Coupling and further reduction form Li2CO3 and possibly CO-containing species.\n4. During charge, Li2CO3 is decomposed on catalytic sites, releasing CO2 (and sometimes O2).\n\nالخطوات الرئيسية (بالعربية بشكل مبسّط):\n1- امتصاص CO₂ من الطور الغازي على سطح أكاسيد نيكل طبقية عالية النيكل.\n2- انتقال الإلكترونات وأيونات Li⁺ لتكوين نوع وسيط مشابه لـ LiCO₂.\n3- تَحوُّل الأنواع الوسيطة إلى Li₂CO₃ ونواتج أخرى حاوية على الكربون.\n4- في الشحن، يساعد السطح التحفيزي على تفكيك Li₂CO₃ وإعادة إطلاق CO₂.\n", "metadata": {"mechanism_id": "M039", "focus_catalyst": "Ni-rich layered oxide", "focus_catalyst_ar": "أكاسيد نيكل طبقية عالية النيكل", "mechanism_topic_en": "charge process", "mechanism_topic_ar": "آلية الشحن", "main_intermediates": ["CO2(ads)", "Li2CO3", "CO(ads)", "Li2C2O4", "Li2O"], "barrier_range_eV": [0.28, 0.614], "overpotential_trend": "Significantly reduced when catalyst is well dispersed", "evidence_type": ["DFT-style analysis (synthetic)", "Conceptual mechanism"], "chunk_type": "mechanism_bilingual"}}
{"text": "Mechanism ID: M040\nTitle: Ni-rich layered oxide–assisted charge process in Li–CO2 cells\nالعنوان بالعربية: آلية الشحن على أكاسيد نيكل طبقية عالية النيكل في بطاريات Li–CO₂\n\nEnglish description:\nThis mechanism describes how Ni-rich layered oxide participates in the charge process of a Li–CO2 battery. \nCO2 from the gas phase is adsorbed on the catalytic surface, reacts with Li+ and electrons, \nand forms solid discharge products such as Li2CO3 together with other intermediates \n(CO2(ads), Li2C2O4, CO2−•). The exact pathway and energy barriers depend on the catalyst surface, \ndefect density, and the local electrolyte environment.\n\nالوصف بالعربية (مختصر):\nتشرح هذه الآلية كيف يساهم أكاسيد نيكل طبقية عالية النيكل في آلية الشحن داخل خلية Li–CO₂. \nيُمتص غاز CO₂ على السطح النشط، ثم يتفاعل مع أيونات الليثيوم والإلكترونات لتكوين نواتج \nمثل Li₂CO₃ وبعض الأنواع الوسيطة (CO2(ads), Li2C2O4, CO2−•). \nشكل السطح والعيوب وبيئة الإلكتروليت تؤثر جميعها في مسار التفاعل وطاقات الحواجز.\n\nKey steps (English, schematic):\n1. CO2(g) → CO2(ads) on Ni-rich layered oxide surface.\n2. CO2(ads) + e− + Li+ → LiCO2-like intermediate.\n3. Coupling and further reduction form Li2CO3 and possibly CO-containing species.\n4. During charge, Li2CO3 is decomposed on catalytic sites, releasing CO2 (and sometimes O2).\n\nالخطوات الرئيسية (بالعربية بشكل مبسّط):\n1- امتصاص CO₂ من الطور الغازي على سطح أكاسيد نيكل طبقية عالية النيكل.\n2- انتقال الإلكترونات وأيونات Li⁺ لتكوين نوع وسيط مشابه لـ LiCO₂.\n3- تَحوُّل الأنواع الوسيطة إلى Li₂CO₃ ونواتج أخرى حاوية على الكربون.\n4- في الشحن، يساعد السطح التحفيزي على تفكيك Li₂CO₃ وإعادة إطلاق CO₂.\n", "metadata": {"mechanism_id": "M040", "focus_catalyst": "Ni-rich layered oxide", "focus_catalyst_ar": "أكاسيد نيكل طبقية عالية النيكل", "mechanism_topic_en": "charge process", "mechanism_topic_ar": "آلية الشحن", "main_intermediates": ["CO2(ads)", "Li2C2O4", "CO2−•"], "barrier_range_eV": [0.31, 0.516], "overpotential_trend": "High during charge, moderate during discharge", "evidence_type": ["DFT-style analysis (synthetic)", "Conceptual mechanism"], "chunk_type": "mechanism_bilingual"}}
{"text": "Mechanism ID: M041\nTitle: Ni-rich layered oxide–assisted full Li–CO2 cycle in Li–CO2 cells\nالعنوان بالعربية: الدورة الكاملة في خلية Li–CO₂ على أكاسيد نيكل طبقية عالية النيكل في بطاريات Li–CO₂\n\nEnglish description:\nThis mechanism describes how Ni-rich layered oxide participates in the full Li–CO2 cycle of a Li–CO2 battery. \nCO2 from the gas phase is adsorbed on the catalytic surface, reacts with Li+ and electrons, \nand forms solid discharge products such as Li2CO3 together with other intermediates \n(Li2O, Li2CO3, CO(ads), LiCO2, CO2(ads)). The exact pathway and energy barriers depend on the catalyst surface, \ndefect density, and the local electrolyte environment.\n\nالوصف بالعربية (مختصر):\nتشرح هذه الآلية كيف يساهم أكاسيد نيكل طبقية عالية النيكل في الدورة الكاملة في خلية Li–CO₂ داخل خلية Li–CO₂. \nيُمتص غاز CO₂ على السطح النشط، ثم يتفاعل مع أيونات الليثيوم والإلكترونات لتكوين نواتج \nمثل Li₂CO₃ وبعض الأنواع الوسيطة (Li2O, Li2CO3, CO(ads), LiCO2, CO2(ads)). \nشكل السطح والعيوب وبيئة الإلكتروليت تؤثر جميعها في مسار التفاعل وطاقات الحواجز.\n\nKey steps (English, schematic):\n1. CO2(g) → CO2(ads) on Ni-rich layered oxide surface.\n2. CO2(ads) + e− + Li+ → LiCO2-like intermediate.\n3. Coupling and further reduction form Li2CO3 and possibly CO-containing species.\n4. During charge, Li2CO3 is decomposed on catalytic sites, releasing CO2 (and sometimes O2).\n\nالخطوات الرئيسية (بالعربية بشكل مبسّط):\n1- امتصاص CO₂ من الطور الغازي على سطح أكاسيد نيكل طبقية عالية النيكل.\n2- انتقال الإلكترونات وأيونات Li⁺ لتكوين نوع وسيط مشابه لـ LiCO₂.\n3- تَحوُّل الأنواع الوسيطة إلى Li₂CO₃ ونواتج أخرى حاوية على الكربون.\n4- في الشحن، يساعد السطح التحفيزي على تفكيك Li₂CO₃ وإعادة إطلاق CO₂.\n", "metadata": {"mechanism_id": "M041", "focus_catalyst": "Ni-rich layered oxide", "focus_catalyst_ar": "أكاسيد نيكل طبقية عالية النيكل", "mechanism_topic_en": "full Li–CO2 cycle", "mechanism_topic_ar": "الدورة الكاملة في خلية Li–CO₂", "main_intermediates": ["Li2O", "Li2CO3", "CO(ads)", "LiCO2", "CO2(ads)"], "barrier_range_eV": [0.267, 0.611], "overpotential_trend": "Moderately reduced vs. pure carbon", "evidence_type": ["DFT-style analysis (synthetic)", "Conceptual mechanism"], "chunk_type": "mechanism_bilingual"}}
{"text": "Mechanism ID: M042\nTitle: Ni-rich layered oxide–assisted discharge process in Li–CO2 cells\nالعنوان بالعربية: آلية التفريغ على أكاسيد نيكل طبقية عالية النيكل في بطاريات Li–CO₂\n\nEnglish description:\nThis mechanism describes how Ni-rich layered oxide participates in the discharge process of a Li–CO2 battery. \nCO2 from the gas phase is adsorbed on the catalytic surface, reacts with Li+ and electrons, \nand forms solid discharge products such as Li2CO3 together with other intermediates \n(Li2O, Li2CO3, LiCO2). The exact pathway and energy barriers depend on the catalyst surface, \ndefect density, and the local electrolyte environment.\n\nالوصف بالعربية (مختصر):\nتشرح هذه الآلية كيف يساهم أكاسيد نيكل طبقية عالية النيكل في آلية التفريغ داخل خلية Li–CO₂. \nيُمتص غاز CO₂ على السطح النشط، ثم يتفاعل مع أيونات الليثيوم والإلكترونات لتكوين نواتج \nمثل Li₂CO₃ وبعض الأنواع الوسيطة (Li2O, Li2CO3, LiCO2). \nشكل السطح والعيوب وبيئة الإلكتروليت تؤثر جميعها في مسار التفاعل وطاقات الحواجز.\n\nKey steps (English, schematic):\n1. CO2(g) → CO2(ads) on Ni-rich layered oxide surface.\n2. CO2(ads) + e− + Li+ → LiCO2-like intermediate.\n3. Coupling and further reduction form Li2CO3 and possibly CO-containing species.\n4. During charge, Li2CO3 is decomposed on catalytic sites, releasing CO2 (and sometimes O2).\n\nالخطوات الرئيسية (بالعربية بشكل مبسّط):\n1- امتصاص CO₂ من الطور الغازي على سطح أكاسيد نيكل طبقية عالية النيكل.\n2- انتقال الإلكترونات وأيونات Li⁺ لتكوين نوع وسيط مشابه لـ LiCO₂.\n3- تَحوُّل الأنواع الوسيطة إلى Li₂CO₃ ونواتج أخرى حاوية على الكربون.\n4- في الشحن، يساعد السطح التحفيزي على تفكيك Li₂CO₃ وإعادة إطلاق CO₂.\n", "metadata": {"mechanism_id": "M042", "focus_catalyst": "Ni-rich layered oxide", "focus_catalyst_ar": "أكاسيد نيكل طبقية عالية النيكل", "mechanism_topic_en": "discharge process", "mechanism_topic_ar": "آلية التفريغ", "main_intermediates": ["Li2O", "Li2CO3", "LiCO2"], "barrier_range_eV": [0.359, 0.572], "overpotential_trend": "High during charge, moderate during discharge", "evidence_type": ["DFT-style analysis (synthetic)", "Conceptual mechanism"], "chunk_type": "mechanism_bilingual"}}
{"text": "Mechanism ID: M043\nTitle: COF host with N-doped linkers–assisted charge process in Li–CO2 cells\nالعنوان بالعربية: آلية الشحن على إطار عضوي تساهمي بروابط غنية بالنيتروجين في بطاريات Li–CO₂\n\nEnglish description:\nThis mechanism describes how COF host with N-doped linkers participates in the charge process of a Li–CO2 battery. \nCO2 from the gas phase is adsorbed on the catalytic surface, reacts with Li+ and electrons, \nand forms solid discharge products such as Li2CO3 together with other intermediates \n(CO2(ads), Li2C2O4, Li2CO3, CO(ads)). The exact pathway and energy barriers depend on the catalyst surface, \ndefect density, and the local electrolyte environment.\n\nالوصف بالعربية (مختصر):\nتشرح هذه الآلية كيف يساهم إطار عضوي تساهمي بروابط غنية بالنيتروجين في آلية الشحن داخل خلية Li–CO₂. \nيُمتص غاز CO₂ على السطح النشط، ثم يتفاعل مع أيونات الليثيوم والإلكترونات لتكوين نواتج \nمثل Li₂CO₃ وبعض الأنواع الوسيطة (CO2(ads), Li2C2O4, Li2CO3, CO(ads)). \nشكل السطح والعيوب وبيئة الإلكتروليت تؤثر جميعها في مسار التفاعل وطاقات الحواجز.\n\nKey steps (English, schematic):\n1. CO2(g) → CO2(ads) on COF host with N-doped linkers surface.\n2. CO2(ads) + e− + Li+ → LiCO2-like intermediate.\n3. Coupling and further reduction form Li2CO3 and possibly CO-containing species.\n4. During charge, Li2CO3 is decomposed on catalytic sites, releasing CO2 (and sometimes O2).\n\nالخطوات الرئيسية (بالعربية بشكل مبسّط):\n1- امتصاص CO₂ من الطور الغازي على سطح إطار عضوي تساهمي بروابط غنية بالنيتروجين.\n2- انتقال الإلكترونات وأيونات Li⁺ لتكوين نوع وسيط مشابه لـ LiCO₂.\n3- تَحوُّل الأنواع الوسيطة إلى Li₂CO₃ ونواتج أخرى حاوية على الكربون.\n4- في الشحن، يساعد السطح التحفيزي على تفكيك Li₂CO₃ وإعادة إطلاق CO₂.\n", "metadata": {"mechanism_id": "M043", "focus_catalyst": "COF host with N-doped linkers", "focus_catalyst_ar": "إطار عضوي تساهمي بروابط غنية بالنيتروجين", "mechanism_topic_en": "charge process", "mechanism_topic_ar": "آلية الشحن", "main_intermediates": ["CO2(ads)", "Li2C2O4", "Li2CO3", "CO(ads)"], "barrier_range_eV": [0.328, 0.639], "overpotential_trend": "Moderately reduced vs. pure carbon", "evidence_type": ["DFT-style analysis (synthetic)", "Conceptual mechanism"], "chunk_type": "mechanism_bilingual"}}
{"text": "Mechanism ID: M044\nTitle: Cu-based MOF–assisted side reactions and by-products in Li–CO2 cells\nالعنوان بالعربية: التفاعلات الجانبية والنواتج الثانوية على إطار فلزي عضوي قائم على النحاس في بطاريات Li–CO₂\n\nEnglish description:\nThis mechanism describes how Cu-based MOF participates in the side reactions and by-products of a Li–CO2 battery. \nCO2 from the gas phase is adsorbed on the catalytic surface, reacts with Li+ and electrons, \nand forms solid discharge products such as Li2CO3 together with other intermediates \n(Li2C2O4, LiCO2, Li2O). The exact pathway and energy barriers depend on the catalyst surface, \ndefect density, and the local electrolyte environment.\n\nالوصف بالعربية (مختصر):\nتشرح هذه الآلية كيف يساهم إطار فلزي عضوي قائم على النحاس في التفاعلات الجانبية والنواتج الثانوية داخل خلية Li–CO₂. \nيُمتص غاز CO₂ على السطح النشط، ثم يتفاعل مع أيونات الليثيوم والإلكترونات لتكوين نواتج \nمثل Li₂CO₃ وبعض الأنواع الوسيطة (Li2C2O4, LiCO2, Li2O). \nشكل السطح والعيوب وبيئة الإلكتروليت تؤثر جميعها في مسار التفاعل وطاقات الحواجز.\n\nKey steps (English, schematic):\n1. CO2(g) → CO2(ads) on Cu-based MOF surface.\n2. CO2(ads) + e− + Li+ → LiCO2-like intermediate.\n3. Coupling and further reduction form Li2CO3 and possibly CO-containing species.\n4. During charge, Li2CO3 is decomposed on catalytic sites, releasing CO2 (and sometimes O2).\n\nالخطوات الرئيسية (بالعربية بشكل مبسّط):\n1- امتصاص CO₂ من الطور الغازي على سطح إطار فلزي عضوي قائم على النحاس.\n2- انتقال الإلكترونات وأيونات Li⁺ لتكوين نوع وسيط مشابه لـ LiCO₂.\n3- تَحوُّل الأنواع الوسيطة إلى Li₂CO₃ ونواتج أخرى حاوية على الكربون.\n4- في الشحن، يساعد السطح التحفيزي على تفكيك Li₂CO₃ وإعادة إطلاق CO₂.\n", "metadata": {"mechanism_id": "M044", "focus_catalyst": "Cu-based MOF", "focus_catalyst_ar": "إطار فلزي عضوي قائم على النحاس", "mechanism_topic_en": "side reactions and by-products", "mechanism_topic_ar": "التفاعلات الجانبية والنواتج الثانوية", "main_intermediates": ["Li2C2O4", "LiCO2", "Li2O"], "barrier_range_eV": [0.297, 0.617], "overpotential_trend": "Significantly reduced when catalyst is well dispersed", "evidence_type": ["DFT-style analysis (synthetic)", "Conceptual mechanism"], "chunk_type": "mechanism_bilingual"}}
{"text": "Mechanism ID: M045\nTitle: Ni-rich layered oxide–assisted side reactions and by-products in Li–CO2 cells\nالعنوان بالعربية: التفاعلات الجانبية والنواتج الثانوية على أكاسيد نيكل طبقية عالية النيكل في بطاريات Li–CO₂\n\nEnglish description:\nThis mechanism describes how Ni-rich layered oxide participates in the side reactions and by-products of a Li–CO2 battery. \nCO2 from the gas phase is adsorbed on the catalytic surface, reacts with Li+ and electrons, \nand forms solid discharge products such as Li2CO3 together with other intermediates \n(Li2CO3, Li2C2O4, LiCO2, CO2−•). The exact pathway and energy barriers depend on the catalyst surface, \ndefect density, and the local electrolyte environment.\n\nالوصف بالعربية (مختصر):\nتشرح هذه الآلية كيف يساهم أكاسيد نيكل طبقية عالية النيكل في التفاعلات الجانبية والنواتج الثانوية داخل خلية Li–CO₂. \nيُمتص غاز CO₂ على السطح النشط، ثم يتفاعل مع أيونات الليثيوم والإلكترونات لتكوين نواتج \nمثل Li₂CO₃ وبعض الأنواع الوسيطة (Li2CO3, Li2C2O4, LiCO2, CO2−•). \nشكل السطح والعيوب وبيئة الإلكتروليت تؤثر جميعها في مسار التفاعل وطاقات الحواجز.\n\nKey steps (English, schematic):\n1. CO2(g) → CO2(ads) on Ni-rich layered oxide surface.\n2. CO2(ads) + e− + Li+ → LiCO2-like intermediate.\n3. Coupling and further reduction form Li2CO3 and possibly CO-containing species.\n4. During charge, Li2CO3 is decomposed on catalytic sites, releasing CO2 (and sometimes O2).\n\nالخطوات الرئيسية (بالعربية بشكل مبسّط):\n1- امتصاص CO₂ من الطور الغازي على سطح أكاسيد نيكل طبقية عالية النيكل.\n2- انتقال الإلكترونات وأيونات Li⁺ لتكوين نوع وسيط مشابه لـ LiCO₂.\n3- تَحوُّل الأنواع الوسيطة إلى Li₂CO₃ ونواتج أخرى حاوية على الكربون.\n4- في الشحن، يساعد السطح التحفيزي على تفكيك Li₂CO₃ وإعادة إطلاق CO₂.\n", "metadata": {"mechanism_id": "M045", "focus_catalyst": "Ni-rich layered oxide", "focus_catalyst_ar": "أكاسيد نيكل طبقية عالية النيكل", "mechanism_topic_en": "side reactions and by-products", "mechanism_topic_ar": "التفاعلات الجانبية والنواتج الثانوية", "main_intermediates": ["Li2CO3", "Li2C2O4", "LiCO2", "CO2−•"], "barrier_range_eV": [0.279, 0.562], "overpotential_trend": "Sensitive to Li2CO3 film morphology", "evidence_type": ["DFT-style analysis (synthetic)", "Conceptual mechanism"], "chunk_type": "mechanism_bilingual"}}
{"text": "Mechanism ID: M046\nTitle: Ru single-atom sites–assisted full Li–CO2 cycle in Li–CO2 cells\nالعنوان بالعربية: الدورة الكاملة في خلية Li–CO₂ على مواقع الروثينيوم أحادي الذرة في بطاريات Li–CO₂\n\nEnglish description:\nThis mechanism describes how Ru single-atom sites participates in the full Li–CO2 cycle of a Li–CO2 battery. \nCO2 from the gas phase is adsorbed on the catalytic surface, reacts with Li+ and electrons, \nand forms solid discharge products such as Li2CO3 together with other intermediates \n(Li2O, CO2(ads), LiCO2, CO(ads)). The exact pathway and energy barriers depend on the catalyst surface, \ndefect density, and the local electrolyte environment.\n\nالوصف بالعربية (مختصر):\nتشرح هذه الآلية كيف يساهم مواقع الروثينيوم أحادي الذرة في الدورة الكاملة في خلية Li–CO₂ داخل خلية Li–CO₂. \nيُمتص غاز CO₂ على السطح النشط، ثم يتفاعل مع أيونات الليثيوم والإلكترونات لتكوين نواتج \nمثل Li₂CO₃ وبعض الأنواع الوسيطة (Li2O, CO2(ads), LiCO2, CO(ads)). \nشكل السطح والعيوب وبيئة الإلكتروليت تؤثر جميعها في مسار التفاعل وطاقات الحواجز.\n\nKey steps (English, schematic):\n1. CO2(g) → CO2(ads) on Ru single-atom sites surface.\n2. CO2(ads) + e− + Li+ → LiCO2-like intermediate.\n3. Coupling and further reduction form Li2CO3 and possibly CO-containing species.\n4. During charge, Li2CO3 is decomposed on catalytic sites, releasing CO2 (and sometimes O2).\n\nالخطوات الرئيسية (بالعربية بشكل مبسّط):\n1- امتصاص CO₂ من الطور الغازي على سطح مواقع الروثينيوم أحادي الذرة.\n2- انتقال الإلكترونات وأيونات Li⁺ لتكوين نوع وسيط مشابه لـ LiCO₂.\n3- تَحوُّل الأنواع الوسيطة إلى Li₂CO₃ ونواتج أخرى حاوية على الكربون.\n4- في الشحن، يساعد السطح التحفيزي على تفكيك Li₂CO₃ وإعادة إطلاق CO₂.\n", "metadata": {"mechanism_id": "M046", "focus_catalyst": "Ru single-atom sites", "focus_catalyst_ar": "مواقع الروثينيوم أحادي الذرة", "mechanism_topic_en": "full Li–CO2 cycle", "mechanism_topic_ar": "الدورة الكاملة في خلية Li–CO₂", "main_intermediates": ["Li2O", "CO2(ads)", "LiCO2", "CO(ads)"], "barrier_range_eV": [0.282, 0.589], "overpotential_trend": "Significantly reduced when catalyst is well dispersed", "evidence_type": ["DFT-style analysis (synthetic)", "Conceptual mechanism"], "chunk_type": "mechanism_bilingual"}}
{"text": "Mechanism ID: M047\nTitle: Hybrid MOF–carbon composite–assisted side reactions and by-products in Li–CO2 cells\nالعنوان بالعربية: التفاعلات الجانبية والنواتج الثانوية على مركب هجين من MOF مع الكربون في بطاريات Li–CO₂\n\nEnglish description:\nThis mechanism describes how Hybrid MOF–carbon composite participates in the side reactions and by-products of a Li–CO2 battery. \nCO2 from the gas phase is adsorbed on the catalytic surface, reacts with Li+ and electrons, \nand forms solid discharge products such as Li2CO3 together with other intermediates \n(Li2C2O4, CO2−•, Li2O, Li2CO3). The exact pathway and energy barriers depend on the catalyst surface, \ndefect density, and the local electrolyte environment.\n\nالوصف بالعربية (مختصر):\nتشرح هذه الآلية كيف يساهم مركب هجين من MOF مع الكربون في التفاعلات الجانبية والنواتج الثانوية داخل خلية Li–CO₂. \nيُمتص غاز CO₂ على السطح النشط، ثم يتفاعل مع أيونات الليثيوم والإلكترونات لتكوين نواتج \nمثل Li₂CO₃ وبعض الأنواع الوسيطة (Li2C2O4, CO2−•, Li2O, Li2CO3). \nشكل السطح والعيوب وبيئة الإلكتروليت تؤثر جميعها في مسار التفاعل وطاقات الحواجز.\n\nKey steps (English, schematic):\n1. CO2(g) → CO2(ads) on Hybrid MOF–carbon composite surface.\n2. CO2(ads) + e− + Li+ → LiCO2-like intermediate.\n3. Coupling and further reduction form Li2CO3 and possibly CO-containing species.\n4. During charge, Li2CO3 is decomposed on catalytic sites, releasing CO2 (and sometimes O2).\n\nالخطوات الرئيسية (بالعربية بشكل مبسّط):\n1- امتصاص CO₂ من الطور الغازي على سطح مركب هجين من MOF مع الكربون.\n2- انتقال الإلكترونات وأيونات Li⁺ لتكوين نوع وسيط مشابه لـ LiCO₂.\n3- تَحوُّل الأنواع الوسيطة إلى Li₂CO₃ ونواتج أخرى حاوية على الكربون.\n4- في الشحن، يساعد السطح التحفيزي على تفكيك Li₂CO₃ وإعادة إطلاق CO₂.\n", "metadata": {"mechanism_id": "M047", "focus_catalyst": "Hybrid MOF–carbon composite", "focus_catalyst_ar": "مركب هجين من MOF مع الكربون", "mechanism_topic_en": "side reactions and by-products", "mechanism_topic_ar": "التفاعلات الجانبية والنواتج الثانوية", "main_intermediates": ["Li2C2O4", "CO2−•", "Li2O", "Li2CO3"], "barrier_range_eV": [0.369, 0.711], "overpotential_trend": "Moderately reduced vs. pure carbon", "evidence_type": ["DFT-style analysis (synthetic)", "Conceptual mechanism"], "chunk_type": "mechanism_bilingual"}}
{"text": "Mechanism ID: M048\nTitle: Mo2C carbide–assisted full Li–CO2 cycle in Li–CO2 cells\nالعنوان بالعربية: الدورة الكاملة في خلية Li–CO₂ على كربيد الموليبدينوم Mo₂C في بطاريات Li–CO₂\n\nEnglish description:\nThis mechanism describes how Mo2C carbide participates in the full Li–CO2 cycle of a Li–CO2 battery. \nCO2 from the gas phase is adsorbed on the catalytic surface, reacts with Li+ and electrons, \nand forms solid discharge products such as Li2CO3 together with other intermediates \n(Li2C2O4, CO(ads), Li2O, LiCO2, CO2(ads)). The exact pathway and energy barriers depend on the catalyst surface, \ndefect density, and the local electrolyte environment.\n\nالوصف بالعربية (مختصر):\nتشرح هذه الآلية كيف يساهم كربيد الموليبدينوم Mo₂C في الدورة الكاملة في خلية Li–CO₂ داخل خلية Li–CO₂. \nيُمتص غاز CO₂ على السطح النشط، ثم يتفاعل مع أيونات الليثيوم والإلكترونات لتكوين نواتج \nمثل Li₂CO₃ وبعض الأنواع الوسيطة (Li2C2O4, CO(ads), Li2O, LiCO2, CO2(ads)). \nشكل السطح والعيوب وبيئة الإلكتروليت تؤثر جميعها في مسار التفاعل وطاقات الحواجز.\n\nKey steps (English, schematic):\n1. CO2(g) → CO2(ads) on Mo2C carbide surface.\n2. CO2(ads) + e− + Li+ → LiCO2-like intermediate.\n3. Coupling and further reduction form Li2CO3 and possibly CO-containing species.\n4. During charge, Li2CO3 is decomposed on catalytic sites, releasing CO2 (and sometimes O2).\n\nالخطوات الرئيسية (بالعربية بشكل مبسّط):\n1- امتصاص CO₂ من الطور الغازي على سطح كربيد الموليبدينوم Mo₂C.\n2- انتقال الإلكترونات وأيونات Li⁺ لتكوين نوع وسيط مشابه لـ LiCO₂.\n3- تَحوُّل الأنواع الوسيطة إلى Li₂CO₃ ونواتج أخرى حاوية على الكربون.\n4- في الشحن، يساعد السطح التحفيزي على تفكيك Li₂CO₃ وإعادة إطلاق CO₂.\n", "metadata": {"mechanism_id": "M048", "focus_catalyst": "Mo2C carbide", "focus_catalyst_ar": "كربيد الموليبدينوم Mo₂C", "mechanism_topic_en": "full Li–CO2 cycle", "mechanism_topic_ar": "الدورة الكاملة في خلية Li–CO₂", "main_intermediates": ["Li2C2O4", "CO(ads)", "Li2O", "LiCO2", "CO2(ads)"], "barrier_range_eV": [0.373, 0.673], "overpotential_trend": "Significantly reduced when catalyst is well dispersed", "evidence_type": ["DFT-style analysis (synthetic)", "Conceptual mechanism"], "chunk_type": "mechanism_bilingual"}}
{"text": "Mechanism ID: M049\nTitle: Co/Mn spinel oxide–assisted charge process in Li–CO2 cells\nالعنوان بالعربية: آلية الشحن على أكاسيد سبينل الكوبالت/المنغنيز في بطاريات Li–CO₂\n\nEnglish description:\nThis mechanism describes how Co/Mn spinel oxide participates in the charge process of a Li–CO2 battery. \nCO2 from the gas phase is adsorbed on the catalytic surface, reacts with Li+ and electrons, \nand forms solid discharge products such as Li2CO3 together with other intermediates \n(CO2(ads), CO(ads), CO2−•). The exact pathway and energy barriers depend on the catalyst surface, \ndefect density, and the local electrolyte environment.\n\nالوصف بالعربية (مختصر):\nتشرح هذه الآلية كيف يساهم أكاسيد سبينل الكوبالت/المنغنيز في آلية الشحن داخل خلية Li–CO₂. \nيُمتص غاز CO₂ على السطح النشط، ثم يتفاعل مع أيونات الليثيوم والإلكترونات لتكوين نواتج \nمثل Li₂CO₃ وبعض الأنواع الوسيطة (CO2(ads), CO(ads), CO2−•). \nشكل السطح والعيوب وبيئة الإلكتروليت تؤثر جميعها في مسار التفاعل وطاقات الحواجز.\n\nKey steps (English, schematic):\n1. CO2(g) → CO2(ads) on Co/Mn spinel oxide surface.\n2. CO2(ads) + e− + Li+ → LiCO2-like intermediate.\n3. Coupling and further reduction form Li2CO3 and possibly CO-containing species.\n4. During charge, Li2CO3 is decomposed on catalytic sites, releasing CO2 (and sometimes O2).\n\nالخطوات الرئيسية (بالعربية بشكل مبسّط):\n1- امتصاص CO₂ من الطور الغازي على سطح أكاسيد سبينل الكوبالت/المنغنيز.\n2- انتقال الإلكترونات وأيونات Li⁺ لتكوين نوع وسيط مشابه لـ LiCO₂.\n3- تَحوُّل الأنواع الوسيطة إلى Li₂CO₃ ونواتج أخرى حاوية على الكربون.\n4- في الشحن، يساعد السطح التحفيزي على تفكيك Li₂CO₃ وإعادة إطلاق CO₂.\n", "metadata": {"mechanism_id": "M049", "focus_catalyst": "Co/Mn spinel oxide", "focus_catalyst_ar": "أكاسيد سبينل الكوبالت/المنغنيز", "mechanism_topic_en": "charge process", "mechanism_topic_ar": "آلية الشحن", "main_intermediates": ["CO2(ads)", "CO(ads)", "CO2−•"], "barrier_range_eV": [0.398, 0.67], "overpotential_trend": "High during charge, moderate during discharge", "evidence_type": ["DFT-style analysis (synthetic)", "Conceptual mechanism"], "chunk_type": "mechanism_bilingual"}}
{"text": "Mechanism ID: M050\nTitle: Hybrid MOF–carbon composite–assisted side reactions and by-products in Li–CO2 cells\nالعنوان بالعربية: التفاعلات الجانبية والنواتج الثانوية على مركب هجين من MOF مع الكربون في بطاريات Li–CO₂\n\nEnglish description:\nThis mechanism describes how Hybrid MOF–carbon composite participates in the side reactions and by-products of a Li–CO2 battery. \nCO2 from the gas phase is adsorbed on the catalytic surface, reacts with Li+ and electrons, \nand forms solid discharge products such as Li2CO3 together with other intermediates \n(Li2O, CO2−•, Li2CO3, CO(ads), Li2C2O4). The exact pathway and energy barriers depend on the catalyst surface, \ndefect density, and the local electrolyte environment.\n\nالوصف بالعربية (مختصر):\nتشرح هذه الآلية كيف يساهم مركب هجين من MOF مع الكربون في التفاعلات الجانبية والنواتج الثانوية داخل خلية Li–CO₂. \nيُمتص غاز CO₂ على السطح النشط، ثم يتفاعل مع أيونات الليثيوم والإلكترونات لتكوين نواتج \nمثل Li₂CO₃ وبعض الأنواع الوسيطة (Li2O, CO2−•, Li2CO3, CO(ads), Li2C2O4). \nشكل السطح والعيوب وبيئة الإلكتروليت تؤثر جميعها في مسار التفاعل وطاقات الحواجز.\n\nKey steps (English, schematic):\n1. CO2(g) → CO2(ads) on Hybrid MOF–carbon composite surface.\n2. CO2(ads) + e− + Li+ → LiCO2-like intermediate.\n3. Coupling and further reduction form Li2CO3 and possibly CO-containing species.\n4. During charge, Li2CO3 is decomposed on catalytic sites, releasing CO2 (and sometimes O2).\n\nالخطوات الرئيسية (بالعربية بشكل مبسّط):\n1- امتصاص CO₂ من الطور الغازي على سطح مركب هجين من MOF مع الكربون.\n2- انتقال الإلكترونات وأيونات Li⁺ لتكوين نوع وسيط مشابه لـ LiCO₂.\n3- تَحوُّل الأنواع الوسيطة إلى Li₂CO₃ ونواتج أخرى حاوية على الكربون.\n4- في الشحن، يساعد السطح التحفيزي على تفكيك Li₂CO₃ وإعادة إطلاق CO₂.\n", "metadata": {"mechanism_id": "M050", "focus_catalyst": "Hybrid MOF–carbon composite", "focus_catalyst_ar": "مركب هجين من MOF مع الكربون", "mechanism_topic_en": "side reactions and by-products", "mechanism_topic_ar": "التفاعلات الجانبية والنواتج الثانوية", "main_intermediates": ["Li2O", "CO2−•", "Li2CO3", "CO(ads)", "Li2C2O4"], "barrier_range_eV": [0.287, 0.568], "overpotential_trend": "High during charge, moderate during discharge", "evidence_type": ["DFT-style analysis (synthetic)", "Conceptual mechanism"], "chunk_type": "mechanism_bilingual"}}
